[{"id":"098|098使字第0081號","permitYearRaw":"098","permitYearRoc":98,"permitYearGregorian":2009,"permitNumber":"098使字第0081號","issueDateRaw":"0980226","issueDate":"2009-02-26","originalPermitNumber":"095建字第0532號","constructionTypeRaw":"新建","constructionType":"new_construction","structureTypeRaw":"鋼骨造(供公眾使用建築物)","structureTypePrimary":"鋼骨造","publicUseStatus":"public_use","zoningRaw":"一般商業區","zoningCategory":"commercial","district":"信義區","primaryAddress":"臺北市信義區松仁路28號","addressCount":11,"addressesSample":["臺北市信義區松仁路28號","臺北市信義區松仁路28號 5樓","臺北市信義區松仁路28號 2樓"],"landSectionCount":1,"landSectionsSample":["臺北市信義區信義段四小段0004-0000號"],"buildingInfo":{"buildingCount":1,"aboveGroundFloors":9,"undergroundFloors":5,"householdCount":11},"buildingArea":{"arcadeSiteAreaSqm":0,"otherSiteAreaSqm":7472,"buildingAreaSqm":6672.23,"legalOpenSpaceAreaSqm":416.04,"aboveGroundShelterAreaSqm":0,"undergroundShelterAreaSqm":12300.5},"buildingHeightM":49.98,"projectCostNtd":800068872,"completionDateRaw":"0971127","completionDate":"2008-11-27","startDateRaw":"0951110","startDate":"2006-11-10","floorSummary":{"floorRecordCount":16,"primaryUses":["停車空間","一般零售業甲、乙組4689.92㎡(B2).停車空間1386.17㎡","一般零售業甲、乙組2728.19 (B2)  餐飲業1207.98 (B3)","防空避難室兼停車空間","一般零售業甲、乙組5047.26㎡(B2)、餐飲業127.60㎡(B3)"],"residentialFloorRecordCount":0,"officeFloorRecordCount":3,"retailFloorRecordCount":4,"parkingFloorRecordCount":4},"parkingSummary":{"parkingRecordCount":4,"carSpaces":177,"motorcycleSpaces":243,"otherSpaces":9},"remarksCount":21,"hasChangeSummary":false,"sourceDetailAvailable":true},{"id":"098|098使字第0082號","permitYearRaw":"098","permitYearRoc":98,"permitYearGregorian":2009,"permitNumber":"098使字第0082號","issueDateRaw":"0980227","issueDate":"2009-02-27","originalPermitNumber":"096建字第0235號","constructionTypeRaw":"新建","constructionType":"new_construction","structureTypeRaw":"RC造(供公眾使用建築物)","structureTypePrimary":"RC造","publicUseStatus":"public_use","zoningRaw":"住宅區","zoningCategory":"residential","district":"信義區","primaryAddress":"臺北市信義區忠孝東路五段236巷39號 4樓","addressCount":7,"addressesSample":["臺北市信義區忠孝東路五段236巷39號 4樓","臺北市信義區忠孝東路五段236巷39號","臺北市信義區忠孝東路五段236巷39號 2樓"],"landSectionCount":1,"landSectionsSample":["臺北市信義區信義段三小段0014-0000號"],"buildingInfo":{"buildingCount":1,"aboveGroundFloors":7,"undergroundFloors":3,"householdCount":7},"buildingArea":{"arcadeSiteAreaSqm":0,"otherSiteAreaSqm":441,"buildingAreaSqm":175.2,"legalOpenSpaceAreaSqm":264.6,"aboveGroundShelterAreaSqm":0,"undergroundShelterAreaSqm":263.03},"buildingHeightM":29.4,"projectCostNtd":17868301,"completionDateRaw":"0980119","completionDate":"2009-01-19","startDateRaw":"0961203","startDate":"2007-12-03","floorSummary":{"floorRecordCount":13,"primaryUses":["防空避難室兼停車空間","停車空間","(H2)集合住宅62.71㎡，管委會使用空間49.53㎡，昇降機4.95㎡，梯廳24.97㎡，樓梯間8.28㎡，合計150.44㎡","(H2)集合住宅","樓梯間"],"residentialFloorRecordCount":8,"officeFloorRecordCount":0,"retailFloorRecordCount":0,"parkingFloorRecordCount":3},"parkingSummary":{"parkingRecordCount":3,"carSpaces":13,"motorcycleSpaces":21},"remarksCount":17,"hasChangeSummary":false,"sourceDetailAvailable":true},{"id":"098|098使字第0108號","permitYearRaw":"098","permitYearRoc":98,"permitYearGregorian":2009,"permitNumber":"098使字第0108號","issueDateRaw":"0980320","issueDate":"2009-03-20","originalPermitNumber":"090建字第0169號","constructionTypeRaw":"新建","constructionType":"new_construction","structureTypeRaw":"RC造、鋼骨造、鋼骨RC造(供公眾使用建築物)","structureTypePrimary":"RC造","publicUseStatus":"public_use","zoningRaw":"商業區（供商務設施使用）","zoningCategory":"commercial","district":"信義區","primaryAddress":"臺北市信義區松智路1號 27樓","addressCount":27,"addressesSample":["臺北市信義區松智路1號 27樓","臺北市信義區松智路1號 9樓","臺北市信義區松智路1號 2樓"],"landSectionCount":1,"landSectionsSample":["臺北市信義區信義段四小段0013-0000號"],"buildingInfo":{"buildingCount":1,"aboveGroundFloors":27,"undergroundFloors":5,"householdCount":27},"buildingArea":{"arcadeSiteAreaSqm":0,"otherSiteAreaSqm":7092,"buildingAreaSqm":2656.61,"legalOpenSpaceAreaSqm":3546,"aboveGroundShelterAreaSqm":0,"undergroundShelterAreaSqm":3937.17},"buildingHeightM":125.66,"projectCostNtd":1127539356,"completionDateRaw":"0980110","completionDate":"2009-01-10","startDateRaw":"0910423","startDate":"2002-04-23","floorSummary":{"floorRecordCount":35,"primaryUses":["停車空間","防空避難室、停車空間","一般事務所(G2)1111.35㎡,一般零售業乙組(B2)1017.14㎡,餐飲業(B3)509.19㎡兼,金融保險業(G1)","一般零售業乙組(B2)兼金融保險業(G1)","餐飲業(B3)兼金融保險業程(G1)"],"residentialFloorRecordCount":0,"officeFloorRecordCount":25,"retailFloorRecordCount":1,"parkingFloorRecordCount":5},"parkingSummary":{"parkingRecordCount":2,"carSpaces":228,"motorcycleSpaces":601},"remarksCount":17,"hasChangeSummary":false,"sourceDetailAvailable":true},{"id":"098|098使字第0138號","permitYearRaw":"098","permitYearRoc":98,"permitYearGregorian":2009,"permitNumber":"098使字第0138號","issueDateRaw":"0980408","issueDate":"2009-04-08","originalPermitNumber":"095建字第0010號","constructionTypeRaw":"新建","constructionType":"new_construction","structureTypeRaw":"RC造(供公眾使用建築物)","structureTypePrimary":"RC造","publicUseStatus":"public_use","zoningRaw":"住3","zoningCategory":"residential","district":"信義區","primaryAddress":"臺北市信義區信義路五段150巷330號 10樓之9","addressCount":108,"addressesSample":["臺北市信義區信義路五段150巷330號 10樓之9","臺北市信義區信義路五段150巷330號 11樓之7","臺北市信義區信義路五段150巷330號 4樓之8"],"landSectionCount":1,"landSectionsSample":["臺北市信義區祥和段三小段0221-0000號"],"buildingInfo":{"buildingCount":1,"aboveGroundFloors":13,"undergroundFloors":3,"householdCount":108},"buildingArea":{"arcadeSiteAreaSqm":0,"otherSiteAreaSqm":1136,"buildingAreaSqm":340.31,"legalOpenSpaceAreaSqm":624.8,"aboveGroundShelterAreaSqm":0,"undergroundShelterAreaSqm":1019.52},"buildingHeightM":40.1,"projectCostNtd":92225625,"completionDateRaw":"0980316","completionDate":"2009-03-16","startDateRaw":"0950719","startDate":"2006-07-19","floorSummary":{"floorRecordCount":19,"primaryUses":["防空避難室兼停車空間","停車空間","停車空間，管理員室，(H2)集合住宅","集合住宅(H2)","樓梯間"],"residentialFloorRecordCount":13,"officeFloorRecordCount":0,"retailFloorRecordCount":0,"parkingFloorRecordCount":3},"parkingSummary":{"parkingRecordCount":6,"carSpaces":70,"motorcycleSpaces":89},"remarksCount":15,"hasChangeSummary":false,"sourceDetailAvailable":true},{"id":"098|098使字第0146號","permitYearRaw":"098","permitYearRoc":98,"permitYearGregorian":2009,"permitNumber":"098使字第0146號","issueDateRaw":"0980416","issueDate":"2009-04-16","originalPermitNumber":"094建字第0072號","constructionTypeRaw":"新建","constructionType":"new_construction","structureTypeRaw":"RC造(供公眾使用建築物)","structureTypePrimary":"RC造","publicUseStatus":"public_use","zoningRaw":"公園用地","zoningCategory":"park","district":"信義區","primaryAddress":"臺北市信義區松勤路100號","addressCount":1,"addressesSample":["臺北市信義區松勤路100號"],"landSectionCount":2,"landSectionsSample":["臺北市信義區信義段五小段0019-0000號","臺北市信義區信義段五小段0018-0000號"],"buildingInfo":{"buildingCount":1,"aboveGroundFloors":7,"undergroundFloors":0,"householdCount":1},"buildingArea":{"otherSiteAreaSqm":9475,"buildingAreaSqm":1419.45,"legalOpenSpaceAreaSqm":8055.55,"undergroundShelterAreaSqm":5216.25},"buildingHeightM":33.35,"projectCostNtd":53640110,"completionDateRaw":"0971022","completionDate":"2008-10-22","startDateRaw":"0960302","startDate":"2007-03-02","floorSummary":{"floorRecordCount":9,"primaryUses":["文康設施，(D1)供低密度使用人口運動休閒之場所","文康設施，(D1)室內球類運動","文康設施，(D1)室內游泳池","文康設施，活動中心，(D1)室內球類運動","樓梯間"],"residentialFloorRecordCount":0,"officeFloorRecordCount":0,"retailFloorRecordCount":0,"parkingFloorRecordCount":0},"parkingSummary":{"parkingRecordCount":3,"carSpaces":56,"motorcycleSpaces":168,"otherSpaces":2},"remarksCount":11,"hasChangeSummary":false,"sourceDetailAvailable":true},{"id":"098|098使字第0152號","permitYearRaw":"098","permitYearRoc":98,"permitYearGregorian":2009,"permitNumber":"098使字第0152號","issueDateRaw":"0980420","issueDate":"2009-04-20","originalPermitNumber":"095建字第0097號","constructionTypeRaw":"新建","constructionType":"new_construction","structureTypeRaw":"RC造(供公眾使用建築物)","structureTypePrimary":"RC造","publicUseStatus":"public_use","zoningRaw":"住3","zoningCategory":"residential","district":"信義區","primaryAddress":"臺北市信義區基隆路二段79巷30弄5號 3樓之1","addressCount":26,"addressesSample":["臺北市信義區基隆路二段79巷30弄5號 3樓之1","臺北市信義區基隆路二段79巷30弄5號 6樓","臺北市信義區基隆路二段79巷30弄5號"],"landSectionCount":1,"landSectionsSample":["臺北市信義區三興段一小段0819-0000號"],"buildingInfo":{"buildingCount":1,"aboveGroundFloors":10,"undergroundFloors":1,"householdCount":26},"buildingArea":{"arcadeSiteAreaSqm":0,"otherSiteAreaSqm":533,"buildingAreaSqm":238.87,"legalOpenSpaceAreaSqm":293.15,"aboveGroundShelterAreaSqm":0,"undergroundShelterAreaSqm":402.16},"buildingHeightM":36.8,"projectCostNtd":27196204,"completionDateRaw":"0971202","completionDate":"2008-12-02","startDateRaw":"0950601","startDate":"2006-06-01","floorSummary":{"floorRecordCount":14,"primaryUses":["防空避難室兼停車空間402.16㎡,停車塔52.45㎡","學前教育設施(F3)141.67㎡、一般零售業甲組(G3)4.3㎡、機車昇降機4.37㎡、其他34.61㎡","(H2)集合住宅","樓梯間","機械房，樓梯間"],"residentialFloorRecordCount":9,"officeFloorRecordCount":0,"retailFloorRecordCount":1,"parkingFloorRecordCount":1},"parkingSummary":{"parkingRecordCount":4,"carSpaces":46,"motorcycleSpaces":52},"remarksCount":16,"hasChangeSummary":false,"sourceDetailAvailable":true},{"id":"098|098使字第0175號","permitYearRaw":"098","permitYearRoc":98,"permitYearGregorian":2009,"permitNumber":"098使字第0175號","issueDateRaw":"0980508","issueDate":"2009-05-08","originalPermitNumber":"095建字第0551號","constructionTypeRaw":"新建","constructionType":"new_construction","structureTypeRaw":"RC造(供公眾使用建築物)","structureTypePrimary":"RC造","publicUseStatus":"public_use","zoningRaw":"住3","zoningCategory":"residential","district":"信義區","primaryAddress":"臺北市信義區忠孝東路五段345巷6號 3樓之1","addressCount":32,"addressesSample":["臺北市信義區忠孝東路五段345巷6號 3樓之1","臺北市信義區忠孝東路五段345巷6號 5樓","臺北市信義區忠孝東路五段345巷6號 9樓"],"landSectionCount":1,"landSectionsSample":["臺北市信義區永吉段四小段0184-0000號"],"buildingInfo":{"buildingCount":1,"aboveGroundFloors":14,"undergroundFloors":3,"householdCount":32},"buildingArea":{"arcadeSiteAreaSqm":0,"otherSiteAreaSqm":1101,"buildingAreaSqm":495.44,"legalOpenSpaceAreaSqm":605.55,"aboveGroundShelterAreaSqm":0,"undergroundShelterAreaSqm":986.69},"buildingHeightM":48.7,"projectCostNtd":96007287,"completionDateRaw":"0980313","completionDate":"2009-03-13","startDateRaw":"0950413","startDate":"2006-04-13","floorSummary":{"floorRecordCount":20,"primaryUses":["防空避難室兼停車空間","停車空間","(H2)公共梯廳:136.34㎡，管理員室:6.00㎡，機車停車空間:166.03㎡，汽車昇降機:46.53㎡，等候空間:37.41㎡，公寓大廈管委空間:84.95㎡，垃圾集中處:8.37㎡，公共空間:7.60㎡","集合住宅(H2)","A棟=梯間:30.94㎡;B棟=梯間:30.94㎡"],"residentialFloorRecordCount":14,"officeFloorRecordCount":0,"retailFloorRecordCount":0,"parkingFloorRecordCount":3},"parkingSummary":{"parkingRecordCount":7,"carSpaces":75,"motorcycleSpaces":102},"remarksCount":18,"hasChangeSummary":false,"sourceDetailAvailable":true},{"id":"098|098使字第0215號","permitYearRaw":"098","permitYearRoc":98,"permitYearGregorian":2009,"permitNumber":"098使字第0215號","issueDateRaw":"0980611","issueDate":"2009-06-11","originalPermitNumber":"098雜字第0017號","constructionTypeRaw":"增建","constructionType":"addition","structureTypeRaw":"鍍鋅鋼浪板(非供公眾使用建築物)","structureTypePrimary":"鍍鋅鋼浪板","publicUseStatus":"non_public_use","zoningRaw":"機關用地","zoningCategory":"government","district":"信義區","primaryAddress":"臺北市信義區仁愛路四段507號","addressCount":1,"addressesSample":["臺北市信義區仁愛路四段507號"],"landSectionCount":3,"landSectionsSample":["臺北市信義區信義段四小段0020-0001號","臺北市信義區信義段四小段0021-0001號","臺北市信義區信義段四小段0037-0028號"],"buildingInfo":{"buildingCount":0,"aboveGroundFloors":0,"undergroundFloors":0,"householdCount":0},"buildingArea":{"arcadeSiteAreaSqm":0,"otherSiteAreaSqm":9834.72,"buildingAreaSqm":9834.72,"legalOpenSpaceAreaSqm":0},"buildingHeightM":1.8,"projectCostNtd":27696,"completionDateRaw":"0980605","completionDate":"2009-06-05","startDateRaw":"0980601","startDate":"2009-06-01","floorSummary":{"floorRecordCount":0,"primaryUses":[],"residentialFloorRecordCount":0,"officeFloorRecordCount":0,"retailFloorRecordCount":0,"parkingFloorRecordCount":0},"parkingSummary":{"parkingRecordCount":0},"remarksCount":0,"hasChangeSummary":false,"sourceDetailAvailable":true},{"id":"098|098使字第0237號","permitYearRaw":"098","permitYearRoc":98,"permitYearGregorian":2009,"permitNumber":"098使字第0237號","issueDateRaw":"0980626","issueDate":"2009-06-26","originalPermitNumber":"095建字第0391號","constructionTypeRaw":"新建","constructionType":"new_construction","structureTypeRaw":"RC造(供公眾使用建築物)","structureTypePrimary":"RC造","publicUseStatus":"public_use","zoningRaw":"機關用地（公共設施用地）","zoningCategory":"government","district":"信義區","primaryAddress":"臺北市信義區信義路五段150巷471號","addressCount":1,"addressesSample":["臺北市信義區信義路五段150巷471號"],"landSectionCount":21,"landSectionsSample":["臺北市信義區祥和段四小段0199-0000號","臺北市信義區祥和段四小段0201-0003號","臺北市信義區祥和段四小段0203-0001號"],"buildingInfo":{"buildingCount":1,"blockCount":1,"aboveGroundFloors":1,"undergroundFloors":0,"householdCount":1},"buildingArea":{"arcadeSiteAreaSqm":0,"otherSiteAreaSqm":22123,"buildingAreaSqm":180,"legalOpenSpaceAreaSqm":292.62,"aboveGroundShelterAreaSqm":0,"undergroundShelterAreaSqm":0},"buildingHeightM":4.4,"projectCostNtd":1206000,"completionDateRaw":"0961115","completionDate":"2007-11-15","startDateRaw":"0950329","startDate":"2006-03-29","floorSummary":{"floorRecordCount":1,"primaryUses":["公務機關(辦公室)"],"residentialFloorRecordCount":0,"officeFloorRecordCount":1,"retailFloorRecordCount":0,"parkingFloorRecordCount":0},"parkingSummary":{"parkingRecordCount":2,"carSpaces":4,"motorcycleSpaces":6},"remarksCount":7,"hasChangeSummary":false,"sourceDetailAvailable":true},{"id":"098|098使字第0245號","permitYearRaw":"098","permitYearRoc":98,"permitYearGregorian":2009,"permitNumber":"098使字第0245號","issueDateRaw":"0980701","issueDate":"2009-07-01","originalPermitNumber":"093建字第0478號","constructionTypeRaw":"新建","constructionType":"new_construction","structureTypeRaw":"RC造(供公眾使用建築物)","structureTypePrimary":"RC造","publicUseStatus":"public_use","zoningRaw":"業務設施區","zoningCategory":"other","district":"信義區","primaryAddress":"臺北市信義區信義路五段115號 5樓之6","addressCount":318,"addressesSample":["臺北市信義區信義路五段115號 5樓之6","臺北市信義區信義路五段115號 6樓之6","臺北市信義區信義路五段115號 7樓之5"],"landSectionCount":2,"landSectionsSample":["臺北市信義區信義段三小段0036-0008號","臺北市信義區信義段三小段0036-0009號"],"buildingInfo":{"buildingCount":1,"blockCount":1,"aboveGroundFloors":19,"undergroundFloors":4,"householdCount":318},"buildingArea":{"arcadeSiteAreaSqm":0,"otherSiteAreaSqm":3082,"buildingAreaSqm":930.3,"legalOpenSpaceAreaSqm":1541,"aboveGroundShelterAreaSqm":0,"undergroundShelterAreaSqm":2149.9},"buildingHeightM":67.8,"projectCostNtd":293731226,"floorSummary":{"floorRecordCount":26,"primaryUses":["防空避難室兼停車空間","停車空間","G-3健身服務業","G-2一般事務所","H-2集合住宅"],"residentialFloorRecordCount":17,"officeFloorRecordCount":1,"retailFloorRecordCount":0,"parkingFloorRecordCount":4},"parkingSummary":{"parkingRecordCount":4,"carSpaces":203,"motorcycleSpaces":321},"remarksCount":23,"hasChangeSummary":false,"sourceDetailAvailable":true},{"id":"098|098使字第0288號","permitYearRaw":"098","permitYearRoc":98,"permitYearGregorian":2009,"permitNumber":"098使字第0288號","issueDateRaw":"0980805","issueDate":"2009-08-05","originalPermitNumber":"096建字第0115號","constructionTypeRaw":"新建","constructionType":"new_construction","structureTypeRaw":"鋼骨RC造(供公眾使用建築物)","structureTypePrimary":"鋼骨RC造","publicUseStatus":"public_use","zoningRaw":"特定業務區","zoningCategory":"mixed_or_special","district":"信義區","primaryAddress":"臺北市信義區松仁路105號 4樓","addressCount":27,"addressesSample":["臺北市信義區松仁路105號 4樓","臺北市信義區松仁路105號 8樓","臺北市信義區松仁路105號 12樓"],"landSectionCount":3,"landSectionsSample":["臺北市信義區信義段三小段0035-0000號","臺北市信義區信義段三小段0035-0005號","臺北市信義區信義段三小段0035-0003號"],"buildingInfo":{"buildingCount":1,"blockCount":1,"aboveGroundFloors":15,"undergroundFloors":3,"householdCount":0},"buildingArea":{"arcadeSiteAreaSqm":0,"otherSiteAreaSqm":5864,"buildingAreaSqm":2340.46,"legalOpenSpaceAreaSqm":3518.4,"aboveGroundShelterAreaSqm":0,"undergroundShelterAreaSqm":3510.32},"buildingHeightM":89.5,"projectCostNtd":439929210,"completionDateRaw":"0980526","completionDate":"2009-05-26","startDateRaw":"0960410","startDate":"2007-04-10","floorSummary":{"floorRecordCount":20,"primaryUses":["(B3)餐飲業(1399.44㎡),停車空間(1782.34㎡),機房","停車空間，機房","防空避難室兼停車空間(3434.21㎡)，機房","(B2)一般零售業甲、乙組","(B3)餐飲業"],"residentialFloorRecordCount":0,"officeFloorRecordCount":0,"retailFloorRecordCount":1,"parkingFloorRecordCount":3},"parkingSummary":{"parkingRecordCount":3,"carSpaces":131,"motorcycleSpaces":350,"otherSpaces":8},"remarksCount":19,"hasChangeSummary":false,"sourceDetailAvailable":true},{"id":"098|098使字第0297號","permitYearRaw":"098","permitYearRoc":98,"permitYearGregorian":2009,"permitNumber":"098使字第0297號","issueDateRaw":"0980810","issueDate":"2009-08-10","originalPermitNumber":"096建字第0086號","constructionTypeRaw":"新建","constructionType":"new_construction","structureTypeRaw":"RC造(供公眾使用建築物)","structureTypePrimary":"RC造","publicUseStatus":"public_use","zoningRaw":"住3","zoningCategory":"residential","district":"信義區","primaryAddress":"臺北市信義區忠孝東路五段71巷12弄10號 4樓","addressCount":78,"addressesSample":["臺北市信義區忠孝東路五段71巷12弄10號 4樓","臺北市信義區忠孝東路五段71巷12弄10號 4樓之5","臺北市信義區忠孝東路五段71巷12弄10號 5樓之3"],"landSectionCount":1,"landSectionsSample":["臺北市信義區雅祥段四小段0699-0000號"],"buildingInfo":{"buildingCount":2,"blockCount":1,"aboveGroundFloors":7,"undergroundFloors":2,"householdCount":78},"buildingArea":{"arcadeSiteAreaSqm":0,"otherSiteAreaSqm":914,"buildingAreaSqm":398.02,"legalOpenSpaceAreaSqm":504.6,"aboveGroundShelterAreaSqm":0,"undergroundShelterAreaSqm":406.29},"buildingHeightM":29.7,"projectCostNtd":40809498,"completionDateRaw":"0980428","completionDate":"2009-04-28","startDateRaw":"0960903","startDate":"2007-09-03","floorSummary":{"floorRecordCount":20,"primaryUses":["防空避難室兼停車空間","停車場、停車空間","停車空間","集合住宅(H2)","機械室"],"residentialFloorRecordCount":14,"officeFloorRecordCount":0,"retailFloorRecordCount":0,"parkingFloorRecordCount":4},"parkingSummary":{"parkingRecordCount":7,"carSpaces":62,"motorcycleSpaces":49},"remarksCount":14,"hasChangeSummary":false,"sourceDetailAvailable":true},{"id":"098|098使字第0309號","permitYearRaw":"098","permitYearRoc":98,"permitYearGregorian":2009,"permitNumber":"098使字第0309號","issueDateRaw":"0980817","issueDate":"2009-08-17","originalPermitNumber":"095建字第0029號","constructionTypeRaw":"新建","constructionType":"new_construction","structureTypeRaw":"鋼骨造、RC造(供公眾使用建築物)","structureTypePrimary":"鋼骨造","publicUseStatus":"public_use","zoningRaw":"住宅區(信義計畫特定專用區)","zoningCategory":"residential","district":"信義區","primaryAddress":"臺北市信義區信義路五段91巷15弄5號","addressCount":23,"addressesSample":["臺北市信義區信義路五段91巷15弄5號","臺北市信義區信義路五段91巷17號 5樓","臺北市信義區信義路五段91巷17號 10樓"],"landSectionCount":1,"landSectionsSample":["臺北市信義區信義段三小段0041-0000號"],"buildingInfo":{"buildingCount":4,"blockCount":4,"aboveGroundFloors":12,"undergroundFloors":2,"householdCount":23},"buildingArea":{"arcadeSiteAreaSqm":0,"otherSiteAreaSqm":2080,"buildingAreaSqm":748.69,"legalOpenSpaceAreaSqm":1248,"aboveGroundShelterAreaSqm":0,"undergroundShelterAreaSqm":1239.63},"buildingHeightM":40.7,"projectCostNtd":126701188,"completionDateRaw":"0980227","completionDate":"2009-02-27","startDateRaw":"0951005","startDate":"2006-10-05","floorSummary":{"floorRecordCount":31,"primaryUses":["防空避難室兼停車空間","停車空間","(H2)集合住宅(272.75平方公尺)，社區管理委員會使用空間(96.92平方公尺)，管理室(3.13平方公尺)","(H2)集合住宅","樓梯間，消防水箱"],"residentialFloorRecordCount":21,"officeFloorRecordCount":0,"retailFloorRecordCount":0,"parkingFloorRecordCount":2},"parkingSummary":{"parkingRecordCount":2,"carSpaces":35,"motorcycleSpaces":84},"remarksCount":22,"hasChangeSummary":false,"sourceDetailAvailable":true},{"id":"098|098使字第0320號","permitYearRaw":"098","permitYearRoc":98,"permitYearGregorian":2009,"permitNumber":"098使字第0320號","issueDateRaw":"0980825","issueDate":"2009-08-25","originalPermitNumber":"095建字第0323號","constructionTypeRaw":"新建","constructionType":"new_construction","structureTypeRaw":"鋼骨造(供公眾使用建築物)","structureTypePrimary":"鋼骨造","publicUseStatus":"public_use","zoningRaw":"機關用地","zoningCategory":"government","district":"信義區","primaryAddress":"臺北市信義區忠孝東路四段551號 2樓","addressCount":17,"addressesSample":["臺北市信義區忠孝東路四段551號 2樓","臺北市信義區忠孝東路四段551號 8樓","臺北市信義區忠孝東路四段551號 9樓"],"landSectionCount":5,"landSectionsSample":["臺北市信義區逸仙段二小段0352-0001號","臺北市信義區逸仙段二小段0352-0002號","臺北市信義區逸仙段二小段0353-0001號"],"buildingInfo":{"buildingCount":1,"blockCount":1,"aboveGroundFloors":16,"undergroundFloors":4,"householdCount":17},"buildingArea":{"arcadeSiteAreaSqm":0,"otherSiteAreaSqm":8180,"buildingAreaSqm":4032.39,"legalOpenSpaceAreaSqm":3272,"aboveGroundShelterAreaSqm":0,"undergroundShelterAreaSqm":2437.07},"buildingHeightM":69.7,"projectCostNtd":402061504,"completionDateRaw":"0980213","completionDate":"2009-02-13","startDateRaw":"0950907","startDate":"2006-09-07","floorSummary":{"floorRecordCount":20,"primaryUses":["防災中心(50.72)，防空避難室兼停車場(1046.12)，13組(B3)公務機關附屬設施，員工飯廳配膳室(375.57),13組(G2)公務機關(698.26)","防空避難室兼停車空間","停車空間","13組,(G2）公務機關","13組,(G2)公務機關"],"residentialFloorRecordCount":0,"officeFloorRecordCount":0,"retailFloorRecordCount":0,"parkingFloorRecordCount":4},"parkingSummary":{"parkingRecordCount":4,"carSpaces":142,"motorcycleSpaces":190},"remarksCount":14,"hasChangeSummary":false,"sourceDetailAvailable":true},{"id":"098|098使字第0322號","permitYearRaw":"098","permitYearRoc":98,"permitYearGregorian":2009,"permitNumber":"098使字第0322號","issueDateRaw":"0980825","issueDate":"2009-08-25","originalPermitNumber":"095建字第0030號","constructionTypeRaw":"新建","constructionType":"new_construction","structureTypeRaw":"鋼骨造、RC造(供公眾使用建築物)","structureTypePrimary":"鋼骨造","publicUseStatus":"public_use","zoningRaw":"住宅區(信義計畫特定專用區)","zoningCategory":"residential","district":"信義區","primaryAddress":"臺北市信義區信義路五段91巷23號 3樓","addressCount":23,"addressesSample":["臺北市信義區信義路五段91巷23號 3樓","臺北市信義區信義路五段91巷23號 7樓","臺北市信義區松勇路53巷58號"],"landSectionCount":1,"landSectionsSample":["臺北市信義區信義段三小段0040-0000號"],"buildingInfo":{"buildingCount":4,"blockCount":4,"aboveGroundFloors":12,"undergroundFloors":2,"householdCount":23},"buildingArea":{"arcadeSiteAreaSqm":0,"otherSiteAreaSqm":2333,"buildingAreaSqm":833.64,"legalOpenSpaceAreaSqm":1399.8,"aboveGroundShelterAreaSqm":0,"undergroundShelterAreaSqm":1381.01},"buildingHeightM":40.7,"projectCostNtd":141574198,"completionDateRaw":"0980522","completionDate":"2009-05-22","startDateRaw":"0951005","startDate":"2006-10-05","floorSummary":{"floorRecordCount":31,"primaryUses":["防空避難室兼停車空間","停車空間","(H2)集合住宅(H2)307.66㎡，社區管理委員會使用空間112.70㎡、管理室3.13㎡","(H2)集合住宅","樓梯間，消防水箱"],"residentialFloorRecordCount":21,"officeFloorRecordCount":0,"retailFloorRecordCount":0,"parkingFloorRecordCount":2},"parkingSummary":{"parkingRecordCount":2,"carSpaces":39,"motorcycleSpaces":94},"remarksCount":21,"hasChangeSummary":false,"sourceDetailAvailable":true},{"id":"098|098使字第0347號","permitYearRaw":"098","permitYearRoc":98,"permitYearGregorian":2009,"permitNumber":"098使字第0347號","issueDateRaw":"0980909","issueDate":"2009-09-09","originalPermitNumber":"095建字第0156號","constructionTypeRaw":"增建","constructionType":"addition","structureTypeRaw":"鋼骨造(供公眾使用建築物)","structureTypePrimary":"鋼骨造","publicUseStatus":"public_use","zoningRaw":"學校用地","zoningCategory":"school","district":"信義區","primaryAddress":"臺北市信義區福德街221巷15號","addressCount":1,"addressesSample":["臺北市信義區福德街221巷15號"],"landSectionCount":15,"landSectionsSample":["臺北市信義區福德段四小段0206-0002號","臺北市信義區福德段四小段0210-0002號","臺北市信義區福德段四小段0212-0000號"],"buildingInfo":{"buildingCount":1,"blockCount":0,"aboveGroundFloors":2,"undergroundFloors":0,"householdCount":1},"buildingArea":{"arcadeSiteAreaSqm":0,"otherSiteAreaSqm":22100.52,"buildingAreaSqm":700.71,"legalOpenSpaceAreaSqm":14365.34,"aboveGroundShelterAreaSqm":0,"undergroundShelterAreaSqm":0},"buildingHeightM":11.56,"projectCostNtd":13659328,"completionDateRaw":"0961225","completionDate":"2007-12-25","startDateRaw":"0950602","startDate":"2006-06-02","floorSummary":{"floorRecordCount":2,"primaryUses":["機械室、管理員室、游泳池","看臺"],"residentialFloorRecordCount":0,"officeFloorRecordCount":0,"retailFloorRecordCount":0,"parkingFloorRecordCount":0},"parkingSummary":{"parkingRecordCount":4,"carSpaces":34,"motorcycleSpaces":61},"remarksCount":9,"hasChangeSummary":false,"sourceDetailAvailable":true},{"id":"098|098使字第0356號","permitYearRaw":"098","permitYearRoc":98,"permitYearGregorian":2009,"permitNumber":"098使字第0356號","issueDateRaw":"0980916","issueDate":"2009-09-16","originalPermitNumber":"095建字第0383號","constructionTypeRaw":"增建","constructionType":"addition","structureTypeRaw":"輕鋼架造(供公眾使用建築物)","structureTypePrimary":"輕鋼架造","publicUseStatus":"public_use","zoningRaw":"商業區(原屬住三,住三之一指定為商三使用 )","zoningCategory":"residential","district":"信義區","primaryAddress":"臺北市信義區忠孝東路五段297號","addressCount":1,"addressesSample":["臺北市信義區忠孝東路五段297號"],"landSectionCount":10,"landSectionsSample":["臺北市信義區永吉段四小段0187-0002號","臺北市信義區永吉段四小段0188-0000號","臺北市信義區永吉段四小段0189-0000號"],"buildingInfo":{"buildingCount":1,"blockCount":0,"aboveGroundFloors":6,"undergroundFloors":5,"householdCount":9},"buildingArea":{"arcadeSiteAreaSqm":0,"otherSiteAreaSqm":5767,"buildingAreaSqm":2870.54,"legalOpenSpaceAreaSqm":2883.5,"aboveGroundShelterAreaSqm":0,"undergroundShelterAreaSqm":0},"buildingHeightM":8.4,"projectCostNtd":1619186,"completionDateRaw":"0970609","completionDate":"2008-06-09","startDateRaw":"0960504","startDate":"2007-05-04","floorSummary":{"floorRecordCount":1,"primaryUses":["(B3)餐飲業1092.33㎡(含本次增建279.17㎡)，(B4)一般旅館業1289.36㎡"],"residentialFloorRecordCount":0,"officeFloorRecordCount":0,"retailFloorRecordCount":0,"parkingFloorRecordCount":0},"parkingSummary":{"parkingRecordCount":4,"carSpaces":174,"motorcycleSpaces":78},"remarksCount":17,"hasChangeSummary":false,"sourceDetailAvailable":true},{"id":"098|098使字第0368號","permitYearRaw":"098","permitYearRoc":98,"permitYearGregorian":2009,"permitNumber":"098使字第0368號","issueDateRaw":"0980922","issueDate":"2009-09-22","originalPermitNumber":"097建字第0185號","constructionTypeRaw":"新建","constructionType":"new_construction","structureTypeRaw":"RC造(供公眾使用建築物)","structureTypePrimary":"RC造","publicUseStatus":"public_use","zoningRaw":"國小用地","zoningCategory":"school","district":"信義區","primaryAddress":"臺北市信義區松仁路226號","addressCount":1,"addressesSample":["臺北市信義區松仁路226號"],"landSectionCount":5,"landSectionsSample":["臺北市信義區吳興段一小段0012-0000號","臺北市信義區吳興段一小段0013-0000號","臺北市信義區吳興段一小段0014-0000號"],"buildingInfo":{"buildingCount":0,"blockCount":1,"aboveGroundFloors":1,"undergroundFloors":0,"householdCount":1},"buildingArea":{"arcadeSiteAreaSqm":0,"otherSiteAreaSqm":18534,"buildingAreaSqm":46.26,"legalOpenSpaceAreaSqm":11120.4,"aboveGroundShelterAreaSqm":0,"undergroundShelterAreaSqm":0},"buildingHeightM":3.05,"projectCostNtd":346783,"completionDateRaw":"0980603","completionDate":"2009-06-03","startDateRaw":"0971014","startDate":"2008-10-14","floorSummary":{"floorRecordCount":1,"primaryUses":["警衛室，(D3，25.63㎡)、大門20.63㎡"],"residentialFloorRecordCount":0,"officeFloorRecordCount":0,"retailFloorRecordCount":0,"parkingFloorRecordCount":0},"parkingSummary":{"parkingRecordCount":2,"carSpaces":1,"motorcycleSpaces":1},"remarksCount":9,"hasChangeSummary":false,"sourceDetailAvailable":true},{"id":"098|098使字第0373號","permitYearRaw":"098","permitYearRoc":98,"permitYearGregorian":2009,"permitNumber":"098使字第0373號","issueDateRaw":"0980924","issueDate":"2009-09-24","originalPermitNumber":"098雜字第0016號","constructionTypeRaw":"新建","constructionType":"new_construction","structureTypeRaw":"磚造、RC造(非供公眾使用建築物)","structureTypePrimary":"磚造","publicUseStatus":"non_public_use","zoningRaw":"住3","zoningCategory":"residential","district":"信義區","primaryAddress":"臺北市信義區莊敬路289巷3弄22號 1樓","addressCount":1,"addressesSample":["臺北市信義區莊敬路289巷3弄22號 1樓"],"landSectionCount":1,"landSectionsSample":["臺北市信義區祥和段二小段0166-0000號"],"buildingInfo":{"buildingCount":0,"blockCount":0,"aboveGroundFloors":0,"undergroundFloors":0,"householdCount":0},"buildingArea":{"arcadeSiteAreaSqm":0,"otherSiteAreaSqm":222,"buildingAreaSqm":0,"legalOpenSpaceAreaSqm":0,"aboveGroundShelterAreaSqm":0,"undergroundShelterAreaSqm":0},"buildingHeightM":3.3,"projectCostNtd":26228.7,"floorSummary":{"floorRecordCount":0,"primaryUses":[],"residentialFloorRecordCount":0,"officeFloorRecordCount":0,"retailFloorRecordCount":0,"parkingFloorRecordCount":0},"parkingSummary":{"parkingRecordCount":0},"remarksCount":4,"hasChangeSummary":false,"sourceDetailAvailable":true},{"id":"098|098使字第0394號","permitYearRaw":"098","permitYearRoc":98,"permitYearGregorian":2009,"permitNumber":"098使字第0394號","issueDateRaw":"0981015","issueDate":"2009-10-15","originalPermitNumber":"092建字第0127號","constructionTypeRaw":"新建","constructionType":"new_construction","structureTypeRaw":"RC造(非供公眾使用建築物)","structureTypePrimary":"RC造","publicUseStatus":"non_public_use","zoningRaw":"公園用地","zoningCategory":"park","district":"信義區","primaryAddress":"臺北市信義區松隆路123巷7號","addressCount":1,"addressesSample":["臺北市信義區松隆路123巷7號"],"landSectionCount":7,"landSectionsSample":["臺北市信義區雅祥段一小段0045-0000號","臺北市信義區雅祥段一小段0046-0000號","臺北市信義區雅祥段一小段0055-0000號"],"buildingInfo":{"buildingCount":1,"blockCount":1,"aboveGroundFloors":1,"undergroundFloors":3,"householdCount":1},"buildingArea":{"otherSiteAreaSqm":3065,"buildingAreaSqm":153.93,"legalOpenSpaceAreaSqm":3006.9},"buildingHeightM":5.15,"projectCostNtd":55305418,"completionDateRaw":"0980508","completionDate":"2009-05-08","startDateRaw":"0921002","startDate":"2003-10-02","floorSummary":{"floorRecordCount":4,"primaryUses":["停車場","梯間、採光花架、通風口"],"residentialFloorRecordCount":0,"officeFloorRecordCount":0,"retailFloorRecordCount":0,"parkingFloorRecordCount":3},"parkingSummary":{"parkingRecordCount":1,"carSpaces":201},"remarksCount":7,"hasChangeSummary":false,"sourceDetailAvailable":true},{"id":"098|098使字第0456號","permitYearRaw":"098","permitYearRoc":98,"permitYearGregorian":2009,"permitNumber":"098使字第0456號","issueDateRaw":"0981204","issueDate":"2009-12-04","originalPermitNumber":"095建字第0346號","constructionTypeRaw":"新建","constructionType":"new_construction","structureTypeRaw":"RC造(供公眾使用建築物)","structureTypePrimary":"RC造","publicUseStatus":"public_use","zoningRaw":"第三種住宅","zoningCategory":"residential","district":"信義區","primaryAddress":"臺北市信義區崇德街63巷27號 2樓之2","addressCount":22,"addressesSample":["臺北市信義區崇德街63巷27號 2樓之2","臺北市信義區崇德街63巷27號 3樓之3","臺北市信義區崇德街63巷27號 4樓之3"],"landSectionCount":1,"landSectionsSample":["臺北市信義區三興段三小段0499-0000號"],"buildingInfo":{"buildingCount":1,"aboveGroundFloors":7,"undergroundFloors":1,"householdCount":22},"buildingArea":{"arcadeSiteAreaSqm":0,"otherSiteAreaSqm":221,"buildingAreaSqm":99.37,"legalOpenSpaceAreaSqm":121.55,"aboveGroundShelterAreaSqm":0,"undergroundShelterAreaSqm":136.55},"buildingHeightM":22,"projectCostNtd":7474497,"completionDateRaw":"0980707","completionDate":"2009-07-07","startDateRaw":"0960413","startDate":"2007-04-13","floorSummary":{"floorRecordCount":11,"primaryUses":["防空避難室兼停車空間","停車空間63.54㎡,梯廳35.83㎡","集合住宅(H2)","樓梯間","水箱，機房"],"residentialFloorRecordCount":6,"officeFloorRecordCount":0,"retailFloorRecordCount":0,"parkingFloorRecordCount":2},"parkingSummary":{"parkingRecordCount":4,"carSpaces":5,"motorcycleSpaces":12},"remarksCount":16,"hasChangeSummary":false,"sourceDetailAvailable":true}]
