[{"id":"108|108使字第0009號","permitYearRaw":"108","permitYearRoc":108,"permitYearGregorian":2019,"permitNumber":"108使字第0009號","issueDateRaw":"1080116","issueDate":"2019-01-16","originalPermitNumber":"104建字第0240號","constructionTypeRaw":"新建","constructionType":"new_construction","structureTypeRaw":"鋼骨RC造(供公眾使用建築物)","structureTypePrimary":"鋼骨RC造","publicUseStatus":"public_use","zoningRaw":"商三特(商二)、住3","zoningCategory":"residential","district":"大安區","primaryAddress":"臺北市大安區復興南路二段150號","addressCount":61,"addressesSample":["臺北市大安區復興南路二段150號","臺北市大安區復興南路二段160巷1號","臺北市大安區復興南路二段152號"],"landSectionCount":2,"landSectionsSample":["臺北市大安區瑞安段二小段0595-0000號","臺北市大安區瑞安段二小段0600-0000號"],"buildingInfo":{"buildingCount":1,"blockCount":1,"aboveGroundFloors":15,"undergroundFloors":4,"householdCount":61},"buildingArea":{"arcadeSiteAreaSqm":91.31,"otherSiteAreaSqm":909.69,"buildingAreaSqm":608.8,"legalOpenSpaceAreaSqm":392.2,"aboveGroundShelterAreaSqm":0,"undergroundShelterAreaSqm":822.19},"buildingHeightM":49.73,"projectCostNtd":154337717,"completionDateRaw":"1071009","completionDate":"2018-10-09","startDateRaw":"1041221","startDate":"2015-12-21","floorSummary":{"floorRecordCount":22,"primaryUses":["防空避難室兼停車空間，配電室、機房、受電室、電氣室，梯間","停車空間，梯間，機房","(G3)一般零售業甲組(不含日用百貨)，門廳，公共梯廳，騎樓(45.11米平方)","(G2)一般事務所，公共梯廳，(H2)集合住宅，梯間","(H2)集合住宅，公共梯廳，梯間"],"residentialFloorRecordCount":14,"officeFloorRecordCount":0,"retailFloorRecordCount":1,"parkingFloorRecordCount":4},"parkingSummary":{"parkingRecordCount":2,"carSpaces":55,"motorcycleSpaces":64},"remarksCount":22,"hasChangeSummary":false,"sourceDetailAvailable":true},{"id":"108|108使字第0013號","permitYearRaw":"108","permitYearRoc":108,"permitYearGregorian":2019,"permitNumber":"108使字第0013號","issueDateRaw":"1080123","issueDate":"2019-01-23","originalPermitNumber":"105雜字第0019號","constructionTypeRaw":"增建","constructionType":"addition","structureTypeRaw":"鋼骨造(供公眾使用建築物)","structureTypePrimary":"鋼骨造","publicUseStatus":"public_use","zoningRaw":"台北工專用地（公共設施用地）","zoningCategory":"industrial","district":"大安區","primaryAddress":"臺北市大安區新生南路一段3號","addressCount":1,"addressesSample":["臺北市大安區新生南路一段3號"],"landSectionCount":2,"landSectionsSample":["臺北市大安區懷生段三小段0205-0000號","臺北市大安區懷生段三小段0206-0000號"],"buildingInfo":{"buildingCount":0,"blockCount":0,"aboveGroundFloors":5,"undergroundFloors":0,"householdCount":0},"buildingArea":{"arcadeSiteAreaSqm":0,"otherSiteAreaSqm":62494,"buildingAreaSqm":17.8,"legalOpenSpaceAreaSqm":0,"aboveGroundShelterAreaSqm":0,"undergroundShelterAreaSqm":0},"buildingHeightM":21.79,"projectCostNtd":2847439,"completionDateRaw":"1070928","completionDate":"2018-09-28","startDateRaw":"1070223","startDate":"2018-02-23","floorSummary":{"floorRecordCount":0,"primaryUses":[],"residentialFloorRecordCount":0,"officeFloorRecordCount":0,"retailFloorRecordCount":0,"parkingFloorRecordCount":0},"parkingSummary":{"parkingRecordCount":0},"remarksCount":4,"hasChangeSummary":false,"sourceDetailAvailable":true},{"id":"108|108使字第0017號","permitYearRaw":"108","permitYearRoc":108,"permitYearGregorian":2019,"permitNumber":"108使字第0017號","issueDateRaw":"1080125","issueDate":"2019-01-25","originalPermitNumber":"105建字第0186號","constructionTypeRaw":"新建","constructionType":"new_construction","structureTypeRaw":"RC造、輕鋼架造(供公眾使用建築物)","structureTypePrimary":"RC造","publicUseStatus":"public_use","zoningRaw":"公園用地","zoningCategory":"park","district":"大安區","primaryAddress":"臺北市大安區新生南路二段1號","addressCount":1,"addressesSample":["臺北市大安區新生南路二段1號"],"landSectionCount":66,"landSectionsSample":["臺北市大安區瑞安段四小段0041-0000號","臺北市大安區瑞安段四小段0140-0000號","臺北市大安區瑞安段四小段0038-0000號"],"buildingInfo":{"buildingCount":1,"blockCount":1,"aboveGroundFloors":1,"undergroundFloors":1,"householdCount":0},"buildingArea":{"arcadeSiteAreaSqm":0,"otherSiteAreaSqm":259337,"buildingAreaSqm":95.34,"legalOpenSpaceAreaSqm":228216.56,"aboveGroundShelterAreaSqm":0,"undergroundShelterAreaSqm":0},"buildingHeightM":6,"projectCostNtd":716486,"completionDateRaw":"1060920","completionDate":"2017-09-20","startDateRaw":"1051213","startDate":"2016-12-13","floorSummary":{"floorRecordCount":3,"primaryUses":["畜水池","廁所","機械室、機房"],"residentialFloorRecordCount":0,"officeFloorRecordCount":0,"retailFloorRecordCount":0,"parkingFloorRecordCount":0},"parkingSummary":{"parkingRecordCount":0},"remarksCount":8,"hasChangeSummary":false,"sourceDetailAvailable":true},{"id":"108|108使字第0020號","permitYearRaw":"108","permitYearRoc":108,"permitYearGregorian":2019,"permitNumber":"108使字第0020號","issueDateRaw":"1080129","issueDate":"2019-01-29","originalPermitNumber":"104建字第0026號","constructionTypeRaw":"增建","constructionType":"addition","structureTypeRaw":"鋼骨造(供公眾使用建築物)","structureTypePrimary":"鋼骨造","publicUseStatus":"public_use","zoningRaw":"大專用地(公共設施用地)","zoningCategory":"mixed_or_special","district":"大安區","primaryAddress":"臺北市大安區和平東路一段129號","addressCount":1,"addressesSample":["臺北市大安區和平東路一段129號"],"landSectionCount":2,"landSectionsSample":["臺北市大安區金華段二小段0674-0000號","臺北市大安區金華段二小段0915-0000號"],"buildingInfo":{"buildingCount":1,"blockCount":1,"aboveGroundFloors":8,"undergroundFloors":2,"householdCount":1},"buildingArea":{"arcadeSiteAreaSqm":0,"otherSiteAreaSqm":32657,"buildingAreaSqm":1195.95,"legalOpenSpaceAreaSqm":19594.2,"undergroundShelterAreaSqm":1191.6},"buildingHeightM":30.6,"projectCostNtd":77307259,"completionDateRaw":"1070626","completionDate":"2018-06-26","startDateRaw":"1040525","startDate":"2015-05-25","floorSummary":{"floorRecordCount":10,"primaryUses":["防空避難室兼停車空間,機房","停車空間,機房","D4學校附屬多功能活動中心"],"residentialFloorRecordCount":0,"officeFloorRecordCount":0,"retailFloorRecordCount":0,"parkingFloorRecordCount":2},"parkingSummary":{"parkingRecordCount":4,"carSpaces":34,"motorcycleSpaces":115,"otherSpaces":2},"remarksCount":20,"hasChangeSummary":false,"sourceDetailAvailable":true},{"id":"108|108使字第0050號","permitYearRaw":"108","permitYearRoc":108,"permitYearGregorian":2019,"permitNumber":"108使字第0050號","issueDateRaw":"1080308","issueDate":"2019-03-08","originalPermitNumber":"106雜字第0038號","constructionTypeRaw":"新建","constructionType":"new_construction","structureTypeRaw":"鋼骨造(供公眾使用建築物)","structureTypePrimary":"鋼骨造","publicUseStatus":"public_use","zoningRaw":"國小用地","zoningCategory":"school","district":"大安區","primaryAddress":"臺北市大安區愛國東路79巷11號","addressCount":1,"addressesSample":["臺北市大安區愛國東路79巷11號"],"landSectionCount":7,"landSectionsSample":["臺北市大安區金華段一小段0635-0000號","臺北市大安區金華段一小段0635-0001號","臺北市大安區金華段一小段0635-0002號"],"buildingInfo":{"buildingCount":0,"blockCount":0,"aboveGroundFloors":4,"undergroundFloors":0,"householdCount":0},"buildingArea":{"arcadeSiteAreaSqm":0,"otherSiteAreaSqm":11060,"buildingAreaSqm":11.36,"legalOpenSpaceAreaSqm":6636,"aboveGroundShelterAreaSqm":0,"undergroundShelterAreaSqm":0},"buildingHeightM":16.64,"projectCostNtd":1943821,"completionDateRaw":"1071207","completionDate":"2018-12-07","startDateRaw":"1070514","startDate":"2018-05-14","floorSummary":{"floorRecordCount":0,"primaryUses":[],"residentialFloorRecordCount":0,"officeFloorRecordCount":0,"retailFloorRecordCount":0,"parkingFloorRecordCount":0},"parkingSummary":{"parkingRecordCount":0},"remarksCount":4,"hasChangeSummary":false,"sourceDetailAvailable":true},{"id":"108|108使字第0053號","permitYearRaw":"108","permitYearRoc":108,"permitYearGregorian":2019,"permitNumber":"108使字第0053號","issueDateRaw":"1080314","issueDate":"2019-03-14","originalPermitNumber":"108建補字第0001號","constructionTypeRaw":"新建","constructionType":"new_construction","structureTypeRaw":"加強磚造(非供公眾使用建築物)","structureTypePrimary":"加強磚造","publicUseStatus":"non_public_use","zoningRaw":"市場用地","zoningCategory":"other","district":"大安區","primaryAddress":"臺北市大安區信義路三段107號","addressCount":1,"addressesSample":["臺北市大安區信義路三段107號"],"landSectionCount":2,"landSectionsSample":["臺北市大安區懷生段二小段0562-0000號","臺北市大安區懷生段二小段0562-0002號"],"buildingInfo":{"buildingCount":1,"blockCount":1,"aboveGroundFloors":2,"undergroundFloors":0,"householdCount":1},"buildingArea":{"arcadeSiteAreaSqm":0,"otherSiteAreaSqm":1895,"buildingAreaSqm":825.87,"legalOpenSpaceAreaSqm":532.12},"buildingHeightM":7.4,"projectCostNtd":11881656,"floorSummary":{"floorRecordCount":3,"primaryUses":["B-2市場","活動中心","水箱"],"residentialFloorRecordCount":0,"officeFloorRecordCount":0,"retailFloorRecordCount":0,"parkingFloorRecordCount":0},"parkingSummary":{"parkingRecordCount":0},"remarksCount":4,"hasChangeSummary":false,"sourceDetailAvailable":true},{"id":"108|108使字第0074號","permitYearRaw":"108","permitYearRoc":108,"permitYearGregorian":2019,"permitNumber":"108使字第0074號","issueDateRaw":"1080430","issueDate":"2019-04-30","originalPermitNumber":"105建字第0069號","constructionTypeRaw":"新建","constructionType":"new_construction","structureTypeRaw":"RC造(供公眾使用建築物)","structureTypePrimary":"RC造","publicUseStatus":"public_use","zoningRaw":"第三種住宅","zoningCategory":"residential","district":"大安區","primaryAddress":"臺北市大安區杭州南路二段63號","addressCount":13,"addressesSample":["臺北市大安區杭州南路二段63號","臺北市大安區杭州南路二段63號 2樓","臺北市大安區杭州南路二段63號 3樓"],"landSectionCount":1,"landSectionsSample":["臺北市大安區金華段四小段0223-0000號"],"buildingInfo":{"buildingCount":1,"blockCount":1,"aboveGroundFloors":7,"undergroundFloors":2,"householdCount":13},"buildingArea":{"arcadeSiteAreaSqm":0,"otherSiteAreaSqm":452,"buildingAreaSqm":203.37,"legalOpenSpaceAreaSqm":248.6,"aboveGroundShelterAreaSqm":0,"undergroundShelterAreaSqm":205.99},"buildingHeightM":26,"projectCostNtd":20804363,"completionDateRaw":"1071219","completionDate":"2018-12-19","startDateRaw":"1051209","startDate":"2016-12-09","floorSummary":{"floorRecordCount":12,"primaryUses":["防空避難室,機房,停車空間","停車空間,機房","一般零售業甲組(排除日用百貨)G3,大廳,管委會使用空間,停車空間","(H2)集合住宅，一般事務所(G2)","(H2)集合住宅"],"residentialFloorRecordCount":6,"officeFloorRecordCount":0,"retailFloorRecordCount":0,"parkingFloorRecordCount":3},"parkingSummary":{"parkingRecordCount":5,"carSpaces":23,"motorcycleSpaces":13},"remarksCount":25,"hasChangeSummary":false,"sourceDetailAvailable":true},{"id":"108|108使字第0084號","permitYearRaw":"108","permitYearRoc":108,"permitYearGregorian":2019,"permitNumber":"108使字第0084號","issueDateRaw":"1080508","issueDate":"2019-05-08","originalPermitNumber":"103建字第0313號","constructionTypeRaw":"新建","constructionType":"new_construction","structureTypeRaw":"RC造(供公眾使用建築物)","structureTypePrimary":"RC造","publicUseStatus":"public_use","zoningRaw":"台灣大學用地〈公共設施用地〉","zoningCategory":"school","district":"大安區","primaryAddress":"臺北市大安區羅斯福路四段1號","addressCount":1,"addressesSample":["臺北市大安區羅斯福路四段1號"],"landSectionCount":25,"landSectionsSample":["臺北市大安區學府段四小段0230-0000號","臺北市大安區學府段四小段0230-0001號","臺北市大安區學府段四小段0230-0002號"],"buildingInfo":{"buildingCount":1,"blockCount":1,"aboveGroundFloors":8,"undergroundFloors":2,"householdCount":1},"buildingArea":{"arcadeSiteAreaSqm":0,"otherSiteAreaSqm":869491,"buildingAreaSqm":2344.56,"legalOpenSpaceAreaSqm":521694.6,"aboveGroundShelterAreaSqm":0,"undergroundShelterAreaSqm":345.65},"buildingHeightM":33.15,"projectCostNtd":155249383,"completionDateRaw":"1061227","completionDate":"2017-12-27","startDateRaw":"1040702","startDate":"2015-07-02","floorSummary":{"floorRecordCount":13,"primaryUses":["教育設施,(D4)防空避難室兼停車空間，教室，機房","教育設施,(D4)設備室","教育設施,(D4)教室","教育設施,附屬一般零售場所(G3),辦公室(G2),學生餐廳(B3)","教育設施,附屬學生餐廳(B3)"],"residentialFloorRecordCount":0,"officeFloorRecordCount":7,"retailFloorRecordCount":0,"parkingFloorRecordCount":1},"parkingSummary":{"parkingRecordCount":5,"carSpaces":59,"motorcycleSpaces":268},"remarksCount":27,"hasChangeSummary":false,"sourceDetailAvailable":true},{"id":"108|108使字第0105號","permitYearRaw":"108","permitYearRoc":108,"permitYearGregorian":2019,"permitNumber":"108使字第0105號","issueDateRaw":"1080603","issueDate":"2019-06-03","originalPermitNumber":"102建字第0136號","constructionTypeRaw":"新建","constructionType":"new_construction","structureTypeRaw":"RC造(供公眾使用建築物)","structureTypePrimary":"RC造","publicUseStatus":"public_use","zoningRaw":"住3－1","zoningCategory":"residential","district":"大安區","primaryAddress":"臺北市大安區金山南路二段219號","addressCount":1,"addressesSample":["臺北市大安區金山南路二段219號"],"landSectionCount":1,"landSectionsSample":["臺北市大安區金華段二小段0961-0000號"],"buildingInfo":{"buildingCount":1,"blockCount":1,"aboveGroundFloors":9,"undergroundFloors":2,"householdCount":1},"buildingArea":{"arcadeSiteAreaSqm":0,"otherSiteAreaSqm":501,"buildingAreaSqm":224.96,"legalOpenSpaceAreaSqm":276.04,"aboveGroundShelterAreaSqm":0,"undergroundShelterAreaSqm":317.63},"buildingHeightM":30.4,"projectCostNtd":32029213,"completionDateRaw":"1070529","completionDate":"2018-05-29","startDateRaw":"1030128","startDate":"2014-01-28","floorSummary":{"floorRecordCount":13,"primaryUses":["防空避難室兼停車空間，配電室、電氣室，蓄水池","停車空間，機房，垃圾儲藏室","(G3)日常用品零售業，電信室，室內停車空間","一般事務所，(G2)","機房"],"residentialFloorRecordCount":0,"officeFloorRecordCount":8,"retailFloorRecordCount":0,"parkingFloorRecordCount":3},"parkingSummary":{"parkingRecordCount":3,"carSpaces":18,"motorcycleSpaces":13},"remarksCount":23,"hasChangeSummary":false,"sourceDetailAvailable":true},{"id":"108|108使字第0107號","permitYearRaw":"108","permitYearRoc":108,"permitYearGregorian":2019,"permitNumber":"108使字第0107號","issueDateRaw":"1080603","issueDate":"2019-06-03","originalPermitNumber":"105建字第0005號","constructionTypeRaw":"新建","constructionType":"new_construction","structureTypeRaw":"RC造(供公眾使用建築物)","structureTypePrimary":"RC造","publicUseStatus":"public_use","zoningRaw":"第三種住宅區","zoningCategory":"residential","district":"大安區","primaryAddress":"臺北市大安區四維路216巷19號 7樓","addressCount":6,"addressesSample":["臺北市大安區四維路216巷19號 7樓","臺北市大安區四維路216巷19號 2樓","臺北市大安區四維路216巷19號 3樓"],"landSectionCount":1,"landSectionsSample":["臺北市大安區大安段三小段0226-0000號"],"buildingInfo":{"buildingCount":1,"blockCount":1,"aboveGroundFloors":7,"undergroundFloors":1,"householdCount":6},"buildingArea":{"arcadeSiteAreaSqm":0,"otherSiteAreaSqm":271,"buildingAreaSqm":121.9,"legalOpenSpaceAreaSqm":149.1,"aboveGroundShelterAreaSqm":0,"undergroundShelterAreaSqm":121.9},"buildingHeightM":22.2,"projectCostNtd":11587000,"completionDateRaw":"1080422","completionDate":"2019-04-22","startDateRaw":"1051115","startDate":"2016-11-15","floorSummary":{"floorRecordCount":11,"primaryUses":["防空避難室","停車空間，樓電梯間","(H2)集合住宅","樓梯間","機房"],"residentialFloorRecordCount":6,"officeFloorRecordCount":0,"retailFloorRecordCount":0,"parkingFloorRecordCount":1},"parkingSummary":{"parkingRecordCount":4,"carSpaces":6,"motorcycleSpaces":7},"remarksCount":21,"hasChangeSummary":false,"sourceDetailAvailable":true},{"id":"108|108使字第0110號","permitYearRaw":"108","permitYearRoc":108,"permitYearGregorian":2019,"permitNumber":"108使字第0110號","issueDateRaw":"1080606","issueDate":"2019-06-06","originalPermitNumber":"105建字第0096號","constructionTypeRaw":"新建","constructionType":"new_construction","structureTypeRaw":"RC造、鋼骨RC造(供公眾使用建築物)","structureTypePrimary":"RC造","publicUseStatus":"public_use","zoningRaw":"國小用地(公共設施用地)","zoningCategory":"school","district":"大安區","primaryAddress":"臺北市大安區大安路二段99號","addressCount":1,"addressesSample":["臺北市大安區大安路二段99號"],"landSectionCount":4,"landSectionsSample":["臺北市大安區大安段二小段0068-0000號","臺北市大安區大安段二小段0070-0000號","臺北市大安區大安段二小段0061-0000號"],"buildingInfo":{"buildingCount":1,"blockCount":1,"aboveGroundFloors":5,"undergroundFloors":2,"householdCount":1},"buildingArea":{"arcadeSiteAreaSqm":0,"otherSiteAreaSqm":20248,"buildingAreaSqm":1586.33,"legalOpenSpaceAreaSqm":0,"aboveGroundShelterAreaSqm":0,"undergroundShelterAreaSqm":1555.56},"buildingHeightM":31.45,"projectCostNtd":144755699,"completionDateRaw":"1071119","completionDate":"2018-11-19","startDateRaw":"1050726","startDate":"2016-07-26","floorSummary":{"floorRecordCount":8,"primaryUses":["(D-3)教育設施(小學)(第五組)，機械室，機房，水箱，泳池","(D-3)教育設施(小學)(第五組)，配電室、機房、受電室、電氣室，防空避難室兼停車場","(D-3)教育設施(小學)(第五組)","(D-3)教育設施(小學)(第五組)，教室，會議室","(D-3)教育設施(小學)(第五組)，教室"],"residentialFloorRecordCount":0,"officeFloorRecordCount":0,"retailFloorRecordCount":0,"parkingFloorRecordCount":1},"parkingSummary":{"parkingRecordCount":2,"carSpaces":35,"motorcycleSpaces":35},"remarksCount":19,"hasChangeSummary":false,"sourceDetailAvailable":true},{"id":"108|108使字第0112號","permitYearRaw":"108","permitYearRoc":108,"permitYearGregorian":2019,"permitNumber":"108使字第0112號","issueDateRaw":"1080606","issueDate":"2019-06-06","originalPermitNumber":"106雜字第0039號","constructionTypeRaw":"新建","constructionType":"new_construction","structureTypeRaw":"鋼骨造、強化玻璃與不銹鋼複合造(供公眾使用建築物)","structureTypePrimary":"鋼骨造","publicUseStatus":"public_use","zoningRaw":"台灣大學用地〈公共設施用地〉","zoningCategory":"school","district":"大安區","primaryAddress":"臺北市大安區羅斯福路四段1號","addressCount":1,"addressesSample":["臺北市大安區羅斯福路四段1號"],"landSectionCount":25,"landSectionsSample":["臺北市大安區學府段四小段0328-0000號","臺北市大安區學府段四小段0329-0000號","臺北市大安區學府段四小段0334-0000號"],"buildingInfo":{"buildingCount":0,"blockCount":0,"aboveGroundFloors":4,"undergroundFloors":0,"householdCount":0},"buildingArea":{"arcadeSiteAreaSqm":0,"otherSiteAreaSqm":869491,"buildingAreaSqm":0,"legalOpenSpaceAreaSqm":521694.6,"aboveGroundShelterAreaSqm":0,"undergroundShelterAreaSqm":0},"buildingHeightM":17.95,"projectCostNtd":2343601,"completionDateRaw":"1080325","completionDate":"2019-03-25","startDateRaw":"1070226","startDate":"2018-02-26","floorSummary":{"floorRecordCount":0,"primaryUses":[],"residentialFloorRecordCount":0,"officeFloorRecordCount":0,"retailFloorRecordCount":0,"parkingFloorRecordCount":0},"parkingSummary":{"parkingRecordCount":0},"remarksCount":4,"hasChangeSummary":false,"sourceDetailAvailable":true},{"id":"108|108使字第0119號","permitYearRaw":"108","permitYearRoc":108,"permitYearGregorian":2019,"permitNumber":"108使字第0119號","issueDateRaw":"1080620","issueDate":"2019-06-20","originalPermitNumber":"105建字第0018號","constructionTypeRaw":"新建","constructionType":"new_construction","structureTypeRaw":"RC造(供公眾使用建築物)","structureTypePrimary":"RC造","publicUseStatus":"public_use","zoningRaw":"第三種住宅","zoningCategory":"residential","district":"大安區","primaryAddress":"臺北市大安區樂利路11巷18號","addressCount":17,"addressesSample":["臺北市大安區樂利路11巷18號","臺北市大安區樂利路11巷18號 2樓","臺北市大安區樂利路11巷18號 3樓"],"landSectionCount":1,"landSectionsSample":["臺北市大安區通化段三小段0706-0000號"],"buildingInfo":{"buildingCount":1,"blockCount":1,"aboveGroundFloors":7,"undergroundFloors":3,"householdCount":17},"buildingArea":{"arcadeSiteAreaSqm":0,"otherSiteAreaSqm":297,"buildingAreaSqm":133.65,"legalOpenSpaceAreaSqm":163.35,"aboveGroundShelterAreaSqm":0,"undergroundShelterAreaSqm":133.65},"buildingHeightM":28.5,"projectCostNtd":14940475,"completionDateRaw":"1071225","completionDate":"2018-12-25","startDateRaw":"1051018","startDate":"2016-10-18","floorSummary":{"floorRecordCount":14,"primaryUses":["防空避難室、機房、台電配電場所","水箱、樓梯間、停車空間","消防機房、停車空間","G3飲食店、第二十一組︰飲食業、停車空間","H-2：集合住宅、第二組：多戶住宅"],"residentialFloorRecordCount":7,"officeFloorRecordCount":0,"retailFloorRecordCount":0,"parkingFloorRecordCount":3},"parkingSummary":{"parkingRecordCount":5,"carSpaces":17,"motorcycleSpaces":9},"remarksCount":23,"hasChangeSummary":false,"sourceDetailAvailable":true},{"id":"108|108使字第0123號","permitYearRaw":"108","permitYearRoc":108,"permitYearGregorian":2019,"permitNumber":"108使字第0123號","issueDateRaw":"1080702","issueDate":"2019-07-02","originalPermitNumber":"102建字第0300號","constructionTypeRaw":"新建","constructionType":"new_construction","structureTypeRaw":"RC造(供公眾使用建築物)","structureTypePrimary":"RC造","publicUseStatus":"public_use","zoningRaw":"住3","zoningCategory":"residential","district":"大安區","primaryAddress":"臺北市大安區敦化南路二段172巷22號","addressCount":17,"addressesSample":["臺北市大安區敦化南路二段172巷22號","臺北市大安區敦化南路二段172巷22號 2樓","臺北市大安區敦化南路二段172巷22號 3樓"],"landSectionCount":1,"landSectionsSample":["臺北市大安區學府段一小段0422-0000號"],"buildingInfo":{"buildingCount":2,"blockCount":1,"aboveGroundFloors":8,"undergroundFloors":3,"householdCount":17},"buildingArea":{"arcadeSiteAreaSqm":0,"otherSiteAreaSqm":594,"buildingAreaSqm":297,"legalOpenSpaceAreaSqm":297,"aboveGroundShelterAreaSqm":0,"undergroundShelterAreaSqm":500.31},"buildingHeightM":25.55,"projectCostNtd":34939929,"completionDateRaw":"1080321","completionDate":"2019-03-21","startDateRaw":"1031008","startDate":"2014-10-08","floorSummary":{"floorRecordCount":14,"primaryUses":["防空避難室兼停車空間","停車空間","第二組多戶住宅(H2)87.27㎡，停車空間158.79㎡，樓電梯間40.94㎡","第二組多戶住宅，(H2)","第二組多戶住宅(H2)"],"residentialFloorRecordCount":8,"officeFloorRecordCount":0,"retailFloorRecordCount":0,"parkingFloorRecordCount":3},"parkingSummary":{"parkingRecordCount":4,"carSpaces":33,"motorcycleSpaces":17},"remarksCount":19,"hasChangeSummary":false,"sourceDetailAvailable":true},{"id":"108|108使字第0124號","permitYearRaw":"108","permitYearRoc":108,"permitYearGregorian":2019,"permitNumber":"108使字第0124號","issueDateRaw":"1080703","issueDate":"2019-07-03","originalPermitNumber":"106建字第0140號","constructionTypeRaw":"新建","constructionType":"new_construction","structureTypeRaw":"鋼構造、RC造(供公眾使用建築物)","structureTypePrimary":"鋼構造","publicUseStatus":"public_use","zoningRaw":"台灣大學用地","zoningCategory":"school","district":"大安區","primaryAddress":"臺北市大安區羅斯福路四段1號","addressCount":1,"addressesSample":["臺北市大安區羅斯福路四段1號"],"landSectionCount":25,"landSectionsSample":["臺北市大安區學府段四小段0217-0000號","臺北市大安區學府段四小段0230-0000號","臺北市大安區學府段四小段0230-0001號"],"buildingInfo":{"buildingCount":1,"blockCount":1,"aboveGroundFloors":2,"undergroundFloors":0,"householdCount":0},"buildingArea":{"arcadeSiteAreaSqm":0,"otherSiteAreaSqm":869491,"buildingAreaSqm":520.45,"legalOpenSpaceAreaSqm":521694.6,"aboveGroundShelterAreaSqm":0,"undergroundShelterAreaSqm":0},"buildingHeightM":8.5,"projectCostNtd":8255839,"completionDateRaw":"1080107","completionDate":"2019-01-07","startDateRaw":"1060111","startDate":"2017-01-11","floorSummary":{"floorRecordCount":2,"primaryUses":["教育設施,(D4)大學,精密溫室,儲藏室,機房","教育設施,(D4)大學,溫室"],"residentialFloorRecordCount":0,"officeFloorRecordCount":0,"retailFloorRecordCount":0,"parkingFloorRecordCount":0},"parkingSummary":{"parkingRecordCount":2,"carSpaces":5,"motorcycleSpaces":16},"remarksCount":16,"hasChangeSummary":false,"sourceDetailAvailable":true},{"id":"108|108使字第0141號","permitYearRaw":"108","permitYearRoc":108,"permitYearGregorian":2019,"permitNumber":"108使字第0141號","issueDateRaw":"1080806","issueDate":"2019-08-06","originalPermitNumber":"106雜字第0009號","constructionTypeRaw":"新建","constructionType":"new_construction","structureTypeRaw":"鋼骨造(供公眾使用建築物)","structureTypePrimary":"鋼骨造","publicUseStatus":"public_use","zoningRaw":"住3","zoningCategory":"residential","district":"大安區","primaryAddress":"臺北市大安區泰順街60巷18弄13號","addressCount":1,"addressesSample":["臺北市大安區泰順街60巷18弄13號"],"landSectionCount":4,"landSectionsSample":["臺北市大安區龍泉段二小段0817-0004號","臺北市大安區龍泉段二小段0847-0000號","臺北市大安區龍泉段二小段0850-0002號"],"buildingInfo":{"buildingCount":1,"blockCount":0,"aboveGroundFloors":5,"undergroundFloors":0,"householdCount":0},"buildingArea":{"otherSiteAreaSqm":283,"buildingAreaSqm":132.82,"legalOpenSpaceAreaSqm":0,"aboveGroundShelterAreaSqm":0,"undergroundShelterAreaSqm":0},"buildingHeightM":15.81,"projectCostNtd":980685,"completionDateRaw":"1070802","completionDate":"2018-08-02","startDateRaw":"1060804","startDate":"2017-08-04","floorSummary":{"floorRecordCount":0,"primaryUses":[],"residentialFloorRecordCount":0,"officeFloorRecordCount":0,"retailFloorRecordCount":0,"parkingFloorRecordCount":0},"parkingSummary":{"parkingRecordCount":0},"remarksCount":6,"hasChangeSummary":false,"sourceDetailAvailable":true},{"id":"108|108使字第0148號","permitYearRaw":"108","permitYearRoc":108,"permitYearGregorian":2019,"permitNumber":"108使字第0148號","issueDateRaw":"1080819","issueDate":"2019-08-19","originalPermitNumber":"108雜字第0017號","constructionTypeRaw":"新建","constructionType":"new_construction","structureTypeRaw":"其他(非供公眾使用建築物)","structureTypePrimary":"其他","publicUseStatus":"non_public_use","zoningRaw":"第三種住宅區、第三種商業區(原屬商二)","zoningCategory":"residential","district":"大安區","primaryAddress":"臺北市大安區基隆路二段172-1號","addressCount":1,"addressesSample":["臺北市大安區基隆路二段172-1號"],"landSectionCount":2,"landSectionsSample":["臺北市大安區通化段三小段0060-0000號","臺北市大安區通化段三小段0060-0003號"],"buildingInfo":{"buildingCount":0,"blockCount":0,"aboveGroundFloors":0,"undergroundFloors":0,"householdCount":0},"buildingArea":{"arcadeSiteAreaSqm":0,"otherSiteAreaSqm":2716,"buildingAreaSqm":0,"legalOpenSpaceAreaSqm":0,"aboveGroundShelterAreaSqm":0,"undergroundShelterAreaSqm":0},"buildingHeightM":0,"projectCostNtd":800000,"completionDateRaw":"1080627","completionDate":"2019-06-27","floorSummary":{"floorRecordCount":0,"primaryUses":[],"residentialFloorRecordCount":0,"officeFloorRecordCount":0,"retailFloorRecordCount":0,"parkingFloorRecordCount":0},"parkingSummary":{"parkingRecordCount":0},"remarksCount":0,"hasChangeSummary":false,"sourceDetailAvailable":true},{"id":"108|108使字第0155號","permitYearRaw":"108","permitYearRoc":108,"permitYearGregorian":2019,"permitNumber":"108使字第0155號","issueDateRaw":"1080903","issueDate":"2019-09-03","originalPermitNumber":"102建字第0315號","constructionTypeRaw":"新建","constructionType":"new_construction","structureTypeRaw":"鋼骨RC造(供公眾使用建築物)","structureTypePrimary":"鋼骨RC造","publicUseStatus":"public_use","zoningRaw":"商三特(商二)、住3","zoningCategory":"residential","district":"大安區","primaryAddress":"臺北市大安區信義路二段66號 13樓之2","addressCount":126,"addressesSample":["臺北市大安區信義路二段66號 13樓之2","臺北市大安區信義路二段66號 14樓之2","臺北市大安區信義路二段66號 3樓之3"],"landSectionCount":20,"landSectionsSample":["臺北市大安區金華段三小段0197-0000號","臺北市大安區金華段三小段0198-0000號","臺北市大安區金華段三小段0199-0000號"],"buildingInfo":{"buildingCount":3,"blockCount":3,"aboveGroundFloors":21,"undergroundFloors":6,"householdCount":126},"buildingArea":{"arcadeSiteAreaSqm":90.83,"otherSiteAreaSqm":1603.17,"buildingAreaSqm":847.7,"legalOpenSpaceAreaSqm":685.9,"aboveGroundShelterAreaSqm":0,"undergroundShelterAreaSqm":1207.96},"buildingHeightM":72.5,"projectCostNtd":267487091,"completionDateRaw":"1070817","completionDate":"2018-08-17","startDateRaw":"1030724","startDate":"2014-07-24","floorSummary":{"floorRecordCount":34,"primaryUses":["停車空間","防空避難室兼停車空間","騎樓","(1)一般零售業(甲組)(便利商店及日用百貨除外)229.57㎡ ,入口門廳114.59㎡ ,停車空間207.99㎡ ,機電空間87.78㎡ ,廁所9.15㎡,其他49.67㎡","集合住宅(H-2)"],"residentialFloorRecordCount":20,"officeFloorRecordCount":0,"retailFloorRecordCount":1,"parkingFloorRecordCount":7},"parkingSummary":{"parkingRecordCount":5,"carSpaces":149,"motorcycleSpaces":135},"remarksCount":32,"hasChangeSummary":false,"sourceDetailAvailable":true},{"id":"108|108使字第0158號","permitYearRaw":"108","permitYearRoc":108,"permitYearGregorian":2019,"permitNumber":"108使字第0158號","issueDateRaw":"1080910","issueDate":"2019-09-10","originalPermitNumber":"106建字第0019號","constructionTypeRaw":"新建","constructionType":"new_construction","structureTypeRaw":"鋼骨造(供公眾使用建築物)","structureTypePrimary":"鋼骨造","publicUseStatus":"public_use","zoningRaw":"住3、第三之一種住宅區、住三〈特〉","zoningCategory":"residential","district":"大安區","primaryAddress":"臺北市大安區金山南路二段188號 3樓之1","addressCount":91,"addressesSample":["臺北市大安區金山南路二段188號 3樓之1","臺北市大安區金山南路二段188號 3樓之2","臺北市大安區金山南路二段188號 3樓之3"],"landSectionCount":4,"landSectionsSample":["臺北市大安區金華段四小段0515-0000號","臺北市大安區金華段四小段0518-0007號","臺北市大安區金華段四小段0519-0000號"],"buildingInfo":{"buildingCount":1,"blockCount":1,"aboveGroundFloors":24,"undergroundFloors":5,"householdCount":91},"buildingArea":{"arcadeSiteAreaSqm":0,"otherSiteAreaSqm":1858,"buildingAreaSqm":498.79,"legalOpenSpaceAreaSqm":1359.21,"aboveGroundShelterAreaSqm":0,"undergroundShelterAreaSqm":498.79},"buildingHeightM":88.1,"projectCostNtd":283278567,"completionDateRaw":"1080520","completionDate":"2019-05-20","startDateRaw":"1060421","startDate":"2017-04-21","floorSummary":{"floorRecordCount":32,"primaryUses":["防空避難室兼停車空間","停車場、停車空間","第十九組 一般零售業甲組(G3)除日用百貨外","集合住宅(H2)318.18㎡、樓電梯間98.89㎡","集合住宅(H2)312.81㎡、樓電梯間98.89㎡"],"residentialFloorRecordCount":22,"officeFloorRecordCount":0,"retailFloorRecordCount":1,"parkingFloorRecordCount":5},"parkingSummary":{"parkingRecordCount":4,"carSpaces":110,"motorcycleSpaces":82},"remarksCount":27,"hasChangeSummary":false,"sourceDetailAvailable":true},{"id":"108|108使字第0176號","permitYearRaw":"108","permitYearRoc":108,"permitYearGregorian":2019,"permitNumber":"108使字第0176號","issueDateRaw":"1081015","issueDate":"2019-10-15","originalPermitNumber":"106雜字第0030號","constructionTypeRaw":"新建","constructionType":"new_construction","structureTypeRaw":"RC造(非供公眾使用建築物)","structureTypePrimary":"RC造","publicUseStatus":"non_public_use","zoningRaw":"住3","zoningCategory":"residential","district":"大安區","primaryAddress":"臺北市大安區杭州南路二段61巷2號","addressCount":1,"addressesSample":["臺北市大安區杭州南路二段61巷2號"],"landSectionCount":0,"landSectionsSample":[],"buildingInfo":{"buildingCount":0,"blockCount":0,"aboveGroundFloors":0,"undergroundFloors":0,"householdCount":0},"buildingArea":{"arcadeSiteAreaSqm":0,"otherSiteAreaSqm":0,"buildingAreaSqm":0,"legalOpenSpaceAreaSqm":0,"aboveGroundShelterAreaSqm":0,"undergroundShelterAreaSqm":0},"buildingHeightM":0,"projectCostNtd":33110,"completionDateRaw":"1080812","completionDate":"2019-08-12","startDateRaw":"1080812","startDate":"2019-08-12","floorSummary":{"floorRecordCount":0,"primaryUses":[],"residentialFloorRecordCount":0,"officeFloorRecordCount":0,"retailFloorRecordCount":0,"parkingFloorRecordCount":0},"parkingSummary":{"parkingRecordCount":0},"remarksCount":1,"hasChangeSummary":false,"sourceDetailAvailable":true},{"id":"108|108使字第0192號","permitYearRaw":"108","permitYearRoc":108,"permitYearGregorian":2019,"permitNumber":"108使字第0192號","issueDateRaw":"1081107","issueDate":"2019-11-07","originalPermitNumber":"104建字第0197號","constructionTypeRaw":"新建","constructionType":"new_construction","structureTypeRaw":"RC造(供公眾使用建築物)","structureTypePrimary":"RC造","publicUseStatus":"public_use","zoningRaw":"住3","zoningCategory":"residential","district":"大安區","primaryAddress":"臺北市大安區羅斯福路三段269巷15號","addressCount":11,"addressesSample":["臺北市大安區羅斯福路三段269巷15號","臺北市大安區羅斯福路三段269巷15號 2樓","臺北市大安區羅斯福路三段269巷15號 3樓"],"landSectionCount":1,"landSectionsSample":["臺北市大安區龍泉段一小段1036-0000號"],"buildingInfo":{"buildingCount":1,"blockCount":0,"aboveGroundFloors":6,"undergroundFloors":1,"householdCount":11},"buildingArea":{"arcadeSiteAreaSqm":0,"otherSiteAreaSqm":117,"buildingAreaSqm":58.18,"legalOpenSpaceAreaSqm":58.5,"aboveGroundShelterAreaSqm":0,"undergroundShelterAreaSqm":58.18},"buildingHeightM":21.8,"projectCostNtd":4371800,"completionDateRaw":"1080625","completionDate":"2019-06-25","startDateRaw":"1050516","startDate":"2016-05-16","floorSummary":{"floorRecordCount":9,"primaryUses":["防空避難室、水箱、電信室","集合住宅(H-2)，停車空間","集合住宅(H-2)","梯間","水箱、梯間"],"residentialFloorRecordCount":6,"officeFloorRecordCount":0,"retailFloorRecordCount":0,"parkingFloorRecordCount":0},"parkingSummary":{"parkingRecordCount":3,"carSpaces":1,"motorcycleSpaces":3},"remarksCount":18,"hasChangeSummary":false,"sourceDetailAvailable":true},{"id":"108|108使字第0194號","permitYearRaw":"108","permitYearRoc":108,"permitYearGregorian":2019,"permitNumber":"108使字第0194號","issueDateRaw":"1081112","issueDate":"2019-11-12","originalPermitNumber":"104建字第0241號","constructionTypeRaw":"新建","constructionType":"new_construction","structureTypeRaw":"RC造(供公眾使用建築物)","structureTypePrimary":"RC造","publicUseStatus":"public_use","zoningRaw":"台灣大學用地〈公共設施用地〉","zoningCategory":"school","district":"大安區","primaryAddress":"臺北市大安區羅斯福路四段1號","addressCount":1,"addressesSample":["臺北市大安區羅斯福路四段1號"],"landSectionCount":25,"landSectionsSample":["臺北市大安區學府段四小段0217-0000號","臺北市大安區學府段四小段0216-0000號","臺北市大安區學府段四小段0230-0000號"],"buildingInfo":{"buildingCount":1,"blockCount":1,"aboveGroundFloors":9,"undergroundFloors":1,"householdCount":1},"buildingArea":{"arcadeSiteAreaSqm":0,"otherSiteAreaSqm":869491,"buildingAreaSqm":1782.13,"legalOpenSpaceAreaSqm":521694.6,"aboveGroundShelterAreaSqm":0,"undergroundShelterAreaSqm":2096.89},"buildingHeightM":38.6,"projectCostNtd":185429824,"completionDateRaw":"1080626","completionDate":"2019-06-26","startDateRaw":"1050715","startDate":"2016-07-15","floorSummary":{"floorRecordCount":11,"primaryUses":["防空避難室兼停車空間，機電空間","教育設施(D4)(第五組)","機械室、機房"],"residentialFloorRecordCount":0,"officeFloorRecordCount":0,"retailFloorRecordCount":0,"parkingFloorRecordCount":1},"parkingSummary":{"parkingRecordCount":4,"carSpaces":55,"motorcycleSpaces":246},"remarksCount":27,"hasChangeSummary":false,"sourceDetailAvailable":true},{"id":"108|108使字第0208號","permitYearRaw":"108","permitYearRoc":108,"permitYearGregorian":2019,"permitNumber":"108使字第0208號","issueDateRaw":"1081206","issueDate":"2019-12-06","originalPermitNumber":"105建字第0092號","constructionTypeRaw":"新建","constructionType":"new_construction","structureTypeRaw":"RC造(非供公眾使用建築物)","structureTypePrimary":"RC造","publicUseStatus":"non_public_use","zoningRaw":"第三種住宅","zoningCategory":"residential","district":"大安區","primaryAddress":"臺北市大安區杭州南路二段25巷39號 2樓之1","addressCount":27,"addressesSample":["臺北市大安區杭州南路二段25巷39號 2樓之1","臺北市大安區杭州南路二段25巷39號 3樓","臺北市大安區杭州南路二段25巷39號 4樓"],"landSectionCount":36,"landSectionsSample":["臺北市大安區金華段三小段0383-0016號","臺北市大安區金華段三小段0384-0000號","臺北市大安區金華段三小段0384-0005號"],"buildingInfo":{"buildingCount":1,"blockCount":1,"aboveGroundFloors":14,"undergroundFloors":4,"householdCount":27},"buildingArea":{"arcadeSiteAreaSqm":0,"otherSiteAreaSqm":989,"buildingAreaSqm":445.05,"legalOpenSpaceAreaSqm":543.95,"aboveGroundShelterAreaSqm":0,"undergroundShelterAreaSqm":730.6},"buildingHeightM":49.9,"projectCostNtd":110659880,"completionDateRaw":"1081001","completionDate":"2019-10-01","startDateRaw":"1050727","startDate":"2016-07-27","floorSummary":{"floorRecordCount":21,"primaryUses":["防空避難室兼停車空間","停車空間","門廳,管委會使用空間","(H2)集合住宅","梯廳"],"residentialFloorRecordCount":13,"officeFloorRecordCount":0,"retailFloorRecordCount":0,"parkingFloorRecordCount":4},"parkingSummary":{"parkingRecordCount":3,"carSpaces":56,"motorcycleSpaces":49},"remarksCount":19,"hasChangeSummary":false,"sourceDetailAvailable":true},{"id":"108|108使字第0220號","permitYearRaw":"108","permitYearRoc":108,"permitYearGregorian":2019,"permitNumber":"108使字第0220號","issueDateRaw":"1081223","issueDate":"2019-12-23","originalPermitNumber":"104建字第0302號","constructionTypeRaw":"新建","constructionType":"new_construction","structureTypeRaw":"RC造(非供公眾使用建築物)","structureTypePrimary":"RC造","publicUseStatus":"non_public_use","zoningRaw":"住3","zoningCategory":"residential","district":"大安區","primaryAddress":"臺北市大安區新生南路一段157巷27號 2樓","addressCount":4,"addressesSample":["臺北市大安區新生南路一段157巷27號 2樓","臺北市大安區新生南路一段157巷27號 3樓","臺北市大安區新生南路一段157巷27號 4樓"],"landSectionCount":1,"landSectionsSample":["臺北市大安區懷生段四小段0179-0000號"],"buildingInfo":{"buildingCount":1,"blockCount":1,"aboveGroundFloors":5,"undergroundFloors":1,"householdCount":4},"buildingArea":{"arcadeSiteAreaSqm":0,"otherSiteAreaSqm":238,"buildingAreaSqm":116.26,"legalOpenSpaceAreaSqm":119,"aboveGroundShelterAreaSqm":0,"undergroundShelterAreaSqm":0},"buildingHeightM":18.9,"projectCostNtd":6468763,"completionDateRaw":"1081122","completionDate":"2019-11-22","startDateRaw":"1051115","startDate":"2016-11-15","floorSummary":{"floorRecordCount":10,"primaryUses":["管委會空間,樓梯間,機械室、機房","門廳15.69㎡,樓梯間8.14㎡,停車空間91.92㎡","(H2)集合住宅","梯廳","機械室,機房"],"residentialFloorRecordCount":5,"officeFloorRecordCount":0,"retailFloorRecordCount":0,"parkingFloorRecordCount":1},"parkingSummary":{"parkingRecordCount":2,"carSpaces":5,"motorcycleSpaces":6},"remarksCount":20,"hasChangeSummary":false,"sourceDetailAvailable":true}]
