[{"id":"108|108使字第0010號","permitYearRaw":"108","permitYearRoc":108,"permitYearGregorian":2019,"permitNumber":"108使字第0010號","issueDateRaw":"1080121","issueDate":"2019-01-21","originalPermitNumber":"104建字第0143號","constructionTypeRaw":"新建","constructionType":"new_construction","structureTypeRaw":"RC造(供公眾使用建築物)","structureTypePrimary":"RC造","publicUseStatus":"public_use","zoningRaw":"住3","zoningCategory":"residential","district":"北投區","primaryAddress":"臺北市北投區石牌路二段315巷34弄22號","addressCount":48,"addressesSample":["臺北市北投區石牌路二段315巷34弄22號","臺北市北投區石牌路二段315巷34弄26號","臺北市北投區石牌路二段315巷34弄28號"],"landSectionCount":1,"landSectionsSample":["臺北市北投區行義段四小段0367-0000號"],"buildingInfo":{"buildingCount":1,"blockCount":1,"aboveGroundFloors":7,"undergroundFloors":2,"householdCount":48},"buildingArea":{"arcadeSiteAreaSqm":0,"otherSiteAreaSqm":478.97,"buildingAreaSqm":206.87,"legalOpenSpaceAreaSqm":272.1,"aboveGroundShelterAreaSqm":0,"undergroundShelterAreaSqm":305.75},"buildingHeightM":25.63,"projectCostNtd":20898372,"completionDateRaw":"1071031","completionDate":"2018-10-31","startDateRaw":"1050307","startDate":"2016-03-07","floorSummary":{"floorRecordCount":12,"primaryUses":["台電配電室、防空避難室兼停車空間","停車場、發電機房、水箱","門廳，(H2)集合住宅","(H2)集合住宅","梯間"],"residentialFloorRecordCount":7,"officeFloorRecordCount":0,"retailFloorRecordCount":0,"parkingFloorRecordCount":2},"parkingSummary":{"parkingRecordCount":6,"carSpaces":16,"motorcycleSpaces":16},"remarksCount":22,"hasChangeSummary":false,"sourceDetailAvailable":true},{"id":"108|108使字第0024號","permitYearRaw":"108","permitYearRoc":108,"permitYearGregorian":2019,"permitNumber":"108使字第0024號","issueDateRaw":"1080131","issueDate":"2019-01-31","originalPermitNumber":"104建字第0025號","constructionTypeRaw":"新建","constructionType":"new_construction","structureTypeRaw":"RC造(供公眾使用建築物)","structureTypePrimary":"RC造","publicUseStatus":"public_use","zoningRaw":"住3","zoningCategory":"residential","district":"北投區","primaryAddress":"臺北市北投區三合街一段82巷119號 3樓","addressCount":85,"addressesSample":["臺北市北投區三合街一段82巷119號 3樓","臺北市北投區三合街一段82巷119號 4樓","臺北市北投區三合街一段82巷119號 5樓"],"landSectionCount":1,"landSectionsSample":["臺北市北投區三合段0005-0000號"],"buildingInfo":{"buildingCount":2,"blockCount":1,"aboveGroundFloors":9,"undergroundFloors":3,"householdCount":85},"buildingArea":{"arcadeSiteAreaSqm":0,"otherSiteAreaSqm":2791.48,"buildingAreaSqm":1256.11,"legalOpenSpaceAreaSqm":1535.37,"undergroundShelterAreaSqm":1514.76},"buildingHeightM":32,"projectCostNtd":183347046,"completionDateRaw":"1071218","completionDate":"2018-12-18","startDateRaw":"1041007","startDate":"2015-10-07","floorSummary":{"floorRecordCount":15,"primaryUses":["防空避難室兼停車空間","停車空間","門廳、車道、管委會使用空間、自行車停車空間","H2集合住宅、管委會使用空間","H2集合住宅"],"residentialFloorRecordCount":8,"officeFloorRecordCount":0,"retailFloorRecordCount":0,"parkingFloorRecordCount":4},"parkingSummary":{"parkingRecordCount":4,"carSpaces":93,"motorcycleSpaces":100},"remarksCount":34,"hasChangeSummary":false,"sourceDetailAvailable":true},{"id":"108|108使字第0032號","permitYearRaw":"108","permitYearRoc":108,"permitYearGregorian":2019,"permitNumber":"108使字第0032號","issueDateRaw":"1080218","issueDate":"2019-02-18","originalPermitNumber":"105建字第0065號","constructionTypeRaw":"新建","constructionType":"new_construction","structureTypeRaw":"RC造(供公眾使用建築物)","structureTypePrimary":"RC造","publicUseStatus":"public_use","zoningRaw":"住三〈特〉","zoningCategory":"residential","district":"北投區","primaryAddress":"臺北市文山區忠順街一段12號","addressCount":81,"addressesSample":["臺北市文山區忠順街一段12號","臺北市文山區忠順街一段16號","臺北市文山區忠順街一段16號 2樓"],"landSectionCount":7,"landSectionsSample":["臺北市文山區實踐段一小段0462-0000號","臺北市文山區實踐段一小段0461-0000號","臺北市文山區實踐段一小段0463-0000號"],"buildingInfo":{"buildingCount":2,"blockCount":1,"aboveGroundFloors":14,"undergroundFloors":4,"householdCount":81},"buildingArea":{"arcadeSiteAreaSqm":0,"otherSiteAreaSqm":2069,"buildingAreaSqm":910.27,"legalOpenSpaceAreaSqm":1158.73,"aboveGroundShelterAreaSqm":0,"undergroundShelterAreaSqm":1422.51},"buildingHeightM":47.1,"projectCostNtd":228208518,"completionDateRaw":"1071212","completionDate":"2018-12-12","startDateRaw":"1050704","startDate":"2016-07-04","floorSummary":{"floorRecordCount":38,"primaryUses":["防空避難室兼停車空間","停車空間","(G3)一般零售業甲組(不含日用百貨)、管理委員會使用空間","(H2)集合住宅","樓梯間"],"residentialFloorRecordCount":24,"officeFloorRecordCount":0,"retailFloorRecordCount":2,"parkingFloorRecordCount":4},"parkingSummary":{"parkingRecordCount":4,"carSpaces":106,"motorcycleSpaces":92,"otherSpaces":1},"remarksCount":31,"hasChangeSummary":false,"sourceDetailAvailable":true},{"id":"108|108使字第0044號","permitYearRaw":"108","permitYearRoc":108,"permitYearGregorian":2019,"permitNumber":"108使字第0044號","issueDateRaw":"1080227","issueDate":"2019-02-27","originalPermitNumber":"066建(北投)字第0226號","constructionTypeRaw":"增建","constructionType":"addition","structureTypeRaw":"RC造(供公眾使用建築物)","structureTypePrimary":"RC造","publicUseStatus":"public_use","zoningRaw":"學校用地","zoningCategory":"school","district":"北投區","primaryAddress":"臺北市北投區復興四路70號","addressCount":1,"addressesSample":["臺北市北投區復興四路70號"],"landSectionCount":24,"landSectionsSample":["臺北市北投區開明段一小段0231-0000號","臺北市北投區開明段一小段0013-0007號","臺北市北投區開明段一小段0013-0012號"],"buildingInfo":{"buildingCount":1,"blockCount":1,"aboveGroundFloors":4,"undergroundFloors":0,"householdCount":1},"buildingArea":{"otherSiteAreaSqm":38850.41,"buildingAreaSqm":116.495,"legalOpenSpaceAreaSqm":23310.25,"aboveGroundShelterAreaSqm":70.65},"buildingHeightM":14.95,"projectCostNtd":931960,"floorSummary":{"floorRecordCount":4,"primaryUses":["防空避難室","教室"],"residentialFloorRecordCount":0,"officeFloorRecordCount":0,"retailFloorRecordCount":0,"parkingFloorRecordCount":0},"parkingSummary":{"parkingRecordCount":0},"remarksCount":9,"hasChangeSummary":false,"sourceDetailAvailable":true},{"id":"108|108使字第0045號","permitYearRaw":"108","permitYearRoc":108,"permitYearGregorian":2019,"permitNumber":"108使字第0045號","issueDateRaw":"1080227","issueDate":"2019-02-27","originalPermitNumber":"066建(北投)字第0227號","constructionTypeRaw":"增建","constructionType":"addition","structureTypeRaw":"RC造(供公眾使用建築物)","structureTypePrimary":"RC造","publicUseStatus":"public_use","zoningRaw":"學校用地","zoningCategory":"school","district":"北投區","primaryAddress":"臺北市北投區新民路2號","addressCount":1,"addressesSample":["臺北市北投區新民路2號"],"landSectionCount":7,"landSectionsSample":["臺北市北投區新民段二小段0539-0000號","臺北市北投區新民段二小段0509-0001號","臺北市北投區新民段二小段0509-0002號"],"buildingInfo":{"buildingCount":1,"blockCount":1,"aboveGroundFloors":5,"undergroundFloors":1,"householdCount":1},"buildingArea":{"otherSiteAreaSqm":19764,"buildingAreaSqm":486.57,"legalOpenSpaceAreaSqm":11858.4},"buildingHeightM":19.5,"projectCostNtd":5328980,"floorSummary":{"floorRecordCount":7,"primaryUses":["防空避難室","教室","樓梯間，儲藏室"],"residentialFloorRecordCount":0,"officeFloorRecordCount":0,"retailFloorRecordCount":0,"parkingFloorRecordCount":0},"parkingSummary":{"parkingRecordCount":0},"remarksCount":9,"hasChangeSummary":false,"sourceDetailAvailable":true},{"id":"108|108使字第0051號","permitYearRaw":"108","permitYearRoc":108,"permitYearGregorian":2019,"permitNumber":"108使字第0051號","issueDateRaw":"1080311","issueDate":"2019-03-11","originalPermitNumber":"105建字第0070號","constructionTypeRaw":"新建","constructionType":"new_construction","structureTypeRaw":"RC造(非供公眾使用建築物)","structureTypePrimary":"RC造","publicUseStatus":"non_public_use","zoningRaw":"第二種住宅區","zoningCategory":"residential","district":"北投區","primaryAddress":"臺北市北投區奇岩路251號","addressCount":4,"addressesSample":["臺北市北投區奇岩路251號","臺北市北投區奇岩路251號 3樓","臺北市北投區奇岩路251-1號"],"landSectionCount":1,"landSectionsSample":["臺北市北投區崇仰段二小段0479-0000號"],"buildingInfo":{"buildingCount":1,"blockCount":1,"aboveGroundFloors":5,"undergroundFloors":2,"householdCount":4},"buildingArea":{"arcadeSiteAreaSqm":0,"otherSiteAreaSqm":459.18,"buildingAreaSqm":159.38,"legalOpenSpaceAreaSqm":298.47,"aboveGroundShelterAreaSqm":0,"undergroundShelterAreaSqm":0},"buildingHeightM":17.1,"projectCostNtd":7239638,"completionDateRaw":"1071024","completionDate":"2018-10-24","startDateRaw":"1051026","startDate":"2016-10-26","floorSummary":{"floorRecordCount":9,"primaryUses":["配電室、機房","停車空間，水箱","集合住宅","樓梯間","水箱"],"residentialFloorRecordCount":5,"officeFloorRecordCount":0,"retailFloorRecordCount":0,"parkingFloorRecordCount":1},"parkingSummary":{"parkingRecordCount":2,"carSpaces":6,"motorcycleSpaces":7},"remarksCount":30,"hasChangeSummary":false,"sourceDetailAvailable":true},{"id":"108|108使字第0055號","permitYearRaw":"108","permitYearRoc":108,"permitYearGregorian":2019,"permitNumber":"108使字第0055號","issueDateRaw":"1080325","issueDate":"2019-03-25","originalPermitNumber":"106建字第0035號","constructionTypeRaw":"新建","constructionType":"new_construction","structureTypeRaw":"RC造(供公眾使用建築物)","structureTypePrimary":"RC造","publicUseStatus":"public_use","zoningRaw":"公園用地(公共設施用地)、公園用地","zoningCategory":"park","district":"北投區","primaryAddress":"臺北市北投區中山路2-1號","addressCount":1,"addressesSample":["臺北市北投區中山路2-1號"],"landSectionCount":37,"landSectionsSample":["臺北市北投區溫泉段一小段0029-0000號","臺北市北投區溫泉段一小段0030-0000號","臺北市北投區溫泉段一小段0056-0005號"],"buildingInfo":{"buildingCount":1,"blockCount":1,"aboveGroundFloors":2,"undergroundFloors":0,"householdCount":1},"buildingArea":{"arcadeSiteAreaSqm":0,"otherSiteAreaSqm":35685.7,"buildingAreaSqm":80.26,"legalOpenSpaceAreaSqm":28574.75,"aboveGroundShelterAreaSqm":0,"undergroundShelterAreaSqm":0},"buildingHeightM":6.75,"projectCostNtd":990843,"completionDateRaw":"1070212","completionDate":"2018-02-12","startDateRaw":"1060405","startDate":"2017-04-05","floorSummary":{"floorRecordCount":2,"primaryUses":["廁所","看臺，空橋"],"residentialFloorRecordCount":0,"officeFloorRecordCount":0,"retailFloorRecordCount":0,"parkingFloorRecordCount":0},"parkingSummary":{"parkingRecordCount":0},"remarksCount":12,"hasChangeSummary":false,"sourceDetailAvailable":true},{"id":"108|108使字第0065號","permitYearRaw":"108","permitYearRoc":108,"permitYearGregorian":2019,"permitNumber":"108使字第0065號","issueDateRaw":"1080415","issueDate":"2019-04-15","originalPermitNumber":"105建字第0166號","constructionTypeRaw":"新建","constructionType":"new_construction","structureTypeRaw":"RC造(供公眾使用建築物)","structureTypePrimary":"RC造","publicUseStatus":"public_use","zoningRaw":"第三種住宅區","zoningCategory":"residential","district":"北投區","primaryAddress":"臺北市北投區崗山路8巷6號","addressCount":32,"addressesSample":["臺北市北投區崗山路8巷6號","臺北市北投區崗山路8巷6號 2樓","臺北市北投區崗山路8巷6號 3樓"],"landSectionCount":1,"landSectionsSample":["臺北市北投區桃源段一小段0583-0000號"],"buildingInfo":{"buildingCount":1,"blockCount":1,"aboveGroundFloors":7,"undergroundFloors":2,"householdCount":32},"buildingArea":{"arcadeSiteAreaSqm":0,"otherSiteAreaSqm":726,"buildingAreaSqm":326.61,"legalOpenSpaceAreaSqm":399.3,"aboveGroundShelterAreaSqm":0,"undergroundShelterAreaSqm":536.97},"buildingHeightM":21.3,"projectCostNtd":36003327,"completionDateRaw":"1071220","completionDate":"2018-12-20","startDateRaw":"1060112","startDate":"2017-01-12","floorSummary":{"floorRecordCount":12,"primaryUses":["防空避難室兼停車空間","停車空間","集合住宅(H2)95.98㎡ ，停車空間,75.35㎡，樓電梯間135.13㎡","集合住宅(H2)","昇降機間"],"residentialFloorRecordCount":7,"officeFloorRecordCount":0,"retailFloorRecordCount":0,"parkingFloorRecordCount":2},"parkingSummary":{"parkingRecordCount":3,"carSpaces":23,"motorcycleSpaces":19},"remarksCount":23,"hasChangeSummary":false,"sourceDetailAvailable":true},{"id":"108|108使字第0073號","permitYearRaw":"108","permitYearRoc":108,"permitYearGregorian":2019,"permitNumber":"108使字第0073號","issueDateRaw":"1080426","issueDate":"2019-04-26","originalPermitNumber":"105建字第0217號","constructionTypeRaw":"新建","constructionType":"new_construction","structureTypeRaw":"RC造(供公眾使用建築物)","structureTypePrimary":"RC造","publicUseStatus":"public_use","zoningRaw":"高中用地(公共設施用地)","zoningCategory":"school","district":"北投區","primaryAddress":"臺北市北投區文林北路77號","addressCount":1,"addressesSample":["臺北市北投區文林北路77號"],"landSectionCount":2,"landSectionsSample":["臺北市北投區文林段二小段0258-0000號","臺北市北投區軟橋段0095-0000號"],"buildingInfo":{"buildingCount":1,"blockCount":1,"aboveGroundFloors":5,"undergroundFloors":0,"householdCount":0},"buildingArea":{"arcadeSiteAreaSqm":0,"otherSiteAreaSqm":75582.91,"buildingAreaSqm":9482.613,"legalOpenSpaceAreaSqm":45349.74,"aboveGroundShelterAreaSqm":0,"undergroundShelterAreaSqm":0},"buildingHeightM":25.1,"projectCostNtd":39645726,"completionDateRaw":"1071214","completionDate":"2018-12-14","startDateRaw":"1060221","startDate":"2017-02-21","floorSummary":{"floorRecordCount":6,"primaryUses":["(第五組：教育設施)(D4)學校附屬活動中心之游泳池、器材室852.2㎡  男女廁所、更衣、淋浴間278.39㎡  機房205.11㎡  大廳、樓梯間87.9㎡","(第五組：教育設施)(D4)學校附屬活動中心之教師辦公室、器材室207.62㎡  空調機房、管道間79.29㎡  梯廳、樓梯間、走廊193.66㎡","(第五組：教育設施)(D4)學校附屬活動中心之擊劍及武術教室872.37㎡  管道間11.9㎡  男女廁所、更衣室163.67㎡  梯廳、樓梯間99.27㎡","(第五組：教育設施)(D4)學校附屬活動中心之空調機房99.3㎡","(第五組：教育設施)(D4)學校附屬活動中心之桌球教室535.64㎡  管道間11.9㎡  梯廳、樓梯間99.27㎡"],"residentialFloorRecordCount":0,"officeFloorRecordCount":1,"retailFloorRecordCount":0,"parkingFloorRecordCount":0},"parkingSummary":{"parkingRecordCount":4,"carSpaces":32,"motorcycleSpaces":66},"remarksCount":17,"hasChangeSummary":false,"sourceDetailAvailable":true},{"id":"108|108使字第0077號","permitYearRaw":"108","permitYearRoc":108,"permitYearGregorian":2019,"permitNumber":"108使字第0077號","issueDateRaw":"1080503","issueDate":"2019-05-03","originalPermitNumber":"104建字第0251號","constructionTypeRaw":"新建","constructionType":"new_construction","structureTypeRaw":"RC造(供公眾使用建築物)","structureTypePrimary":"RC造","publicUseStatus":"public_use","zoningRaw":"第三種住宅","zoningCategory":"residential","district":"北投區","primaryAddress":"臺北市北投區文化三路170號 10樓","addressCount":35,"addressesSample":["臺北市北投區文化三路170號 10樓","臺北市北投區文化三路172號 2樓","臺北市北投區文化三路172號 3樓"],"landSectionCount":1,"landSectionsSample":["臺北市北投區秀山段二小段0663-0000號"],"buildingInfo":{"buildingCount":1,"blockCount":1,"aboveGroundFloors":10,"undergroundFloors":2,"householdCount":35},"buildingArea":{"arcadeSiteAreaSqm":0,"otherSiteAreaSqm":974,"buildingAreaSqm":325.04,"legalOpenSpaceAreaSqm":535.7,"aboveGroundShelterAreaSqm":0,"undergroundShelterAreaSqm":646.47},"buildingHeightM":43.65,"projectCostNtd":48479823,"completionDateRaw":"1071024","completionDate":"2018-10-24","startDateRaw":"1050114","startDate":"2016-01-14","floorSummary":{"floorRecordCount":16,"primaryUses":["防空避難室兼停車空間","停車場、停車空間","停車空間，梯廳，管理委員會使用空間","第二組:多戶住宅(二)集合住宅(H2)","樓梯間，梯廳"],"residentialFloorRecordCount":10,"officeFloorRecordCount":0,"retailFloorRecordCount":0,"parkingFloorRecordCount":3},"parkingSummary":{"parkingRecordCount":5,"carSpaces":24,"motorcycleSpaces":30},"remarksCount":23,"hasChangeSummary":false,"sourceDetailAvailable":true},{"id":"108|108使字第0095號","permitYearRaw":"108","permitYearRoc":108,"permitYearGregorian":2019,"permitNumber":"108使字第0095號","issueDateRaw":"1080521","issueDate":"2019-05-21","originalPermitNumber":"104建字第0209號","constructionTypeRaw":"新建","constructionType":"new_construction","structureTypeRaw":"鋼骨造(供公眾使用建築物)","structureTypePrimary":"鋼骨造","publicUseStatus":"public_use","zoningRaw":"科技工業區","zoningCategory":"industrial","district":"北投區","primaryAddress":"臺北市北投區立德路115號","addressCount":34,"addressesSample":["臺北市北投區立德路115號","臺北市北投區立德路115-1號","臺北市北投區立德路115-2號"],"landSectionCount":3,"landSectionsSample":["臺北市北投區豐年段四小段0438-0001號","臺北市北投區豐年段四小段0408-0000號","臺北市北投區豐年段四小段0408-0001號"],"buildingInfo":{"buildingCount":2,"blockCount":2,"aboveGroundFloors":16,"undergroundFloors":4,"householdCount":34},"buildingArea":{"arcadeSiteAreaSqm":0,"otherSiteAreaSqm":37428.62,"buildingAreaSqm":5612.94,"legalOpenSpaceAreaSqm":20585.74,"aboveGroundShelterAreaSqm":0,"undergroundShelterAreaSqm":11703.03},"buildingHeightM":66.5,"projectCostNtd":2532619707,"completionDateRaw":"1080213","completionDate":"2019-02-13","startDateRaw":"1050510","startDate":"2016-05-10","floorSummary":{"floorRecordCount":24,"primaryUses":["策略性產業，(G2)資訊服務業、機房、防空避難室兼停車空間，配電室","停車空間、機房","停車空間、機房、水箱","策略性產業，(G2)資訊服務業，員工附屬設施","策略性產業，(G2)資訊服務業"],"residentialFloorRecordCount":0,"officeFloorRecordCount":0,"retailFloorRecordCount":0,"parkingFloorRecordCount":4},"parkingSummary":{"parkingRecordCount":5,"carSpaces":1053,"motorcycleSpaces":1067,"otherSpaces":9},"remarksCount":38,"hasChangeSummary":false,"sourceDetailAvailable":true},{"id":"108|108使字第0099號","permitYearRaw":"108","permitYearRoc":108,"permitYearGregorian":2019,"permitNumber":"108使字第0099號","issueDateRaw":"1080527","issueDate":"2019-05-27","originalPermitNumber":"105建字第0200號","constructionTypeRaw":"新建","constructionType":"new_construction","structureTypeRaw":"RC造(供公眾使用建築物)","structureTypePrimary":"RC造","publicUseStatus":"public_use","zoningRaw":"住3","zoningCategory":"residential","district":"北投區","primaryAddress":"臺北市北投區三合街一段99號","addressCount":7,"addressesSample":["臺北市北投區三合街一段99號","臺北市北投區三合街一段99號 2樓","臺北市北投區三合街一段99號 3樓"],"landSectionCount":1,"landSectionsSample":["臺北市北投區三合段0054-0000號"],"buildingInfo":{"buildingCount":1,"blockCount":1,"aboveGroundFloors":7,"undergroundFloors":4,"householdCount":7},"buildingArea":{"arcadeSiteAreaSqm":0,"otherSiteAreaSqm":2200.84,"buildingAreaSqm":990.31,"legalOpenSpaceAreaSqm":1210.46,"aboveGroundShelterAreaSqm":0,"undergroundShelterAreaSqm":998.15},"buildingHeightM":25,"projectCostNtd":115411886,"completionDateRaw":"1080129","completionDate":"2019-01-29","startDateRaw":"1060109","startDate":"2017-01-09","floorSummary":{"floorRecordCount":13,"primaryUses":["宗祠及宗教建築(附屬餐廳G3)、停車空間","防空避難室兼停車空間","停車空間","宗祠及宗教建築(小禪堂)(E)、(小佛堂)(E)、梯廳","宗祠及宗教建築(教室)(E)、(禪堂)(E)"],"residentialFloorRecordCount":0,"officeFloorRecordCount":0,"retailFloorRecordCount":0,"parkingFloorRecordCount":4},"parkingSummary":{"parkingRecordCount":4,"carSpaces":85,"motorcycleSpaces":29,"otherSpaces":1},"remarksCount":22,"hasChangeSummary":false,"sourceDetailAvailable":true},{"id":"108|108使字第0106號","permitYearRaw":"108","permitYearRoc":108,"permitYearGregorian":2019,"permitNumber":"108使字第0106號","issueDateRaw":"1080603","issueDate":"2019-06-03","originalPermitNumber":"105建字第0049號","constructionTypeRaw":"新建","constructionType":"new_construction","structureTypeRaw":"RC造(供公眾使用建築物)","structureTypePrimary":"RC造","publicUseStatus":"public_use","zoningRaw":"第三種住宅區","zoningCategory":"residential","district":"北投區","primaryAddress":"臺北市北投區清江里崇仁路一段5號","addressCount":8,"addressesSample":["臺北市北投區清江里崇仁路一段5號","臺北市北投區清江里崇仁路一段5號 2樓","臺北市北投區清江里崇仁路一段5號 3樓"],"landSectionCount":2,"landSectionsSample":["臺北市北投區奇岩段四小段0131-0000號","臺北市北投區奇岩段四小段0132-0000號"],"buildingInfo":{"buildingCount":1,"blockCount":1,"aboveGroundFloors":8,"undergroundFloors":2,"householdCount":8},"buildingArea":{"arcadeSiteAreaSqm":0,"otherSiteAreaSqm":474,"buildingAreaSqm":212.6,"legalOpenSpaceAreaSqm":260.7,"aboveGroundShelterAreaSqm":0,"undergroundShelterAreaSqm":353.28},"buildingHeightM":26.2,"projectCostNtd":22644441,"completionDateRaw":"1071225","completionDate":"2018-12-25","startDateRaw":"1050711","startDate":"2016-07-11","floorSummary":{"floorRecordCount":15,"primaryUses":["防空避難室兼停車空間,台電配電室、電信機房","停車空間,消防機房,蓄水池,緊集發電機室","G3(第十九組/二十一組：一般零售業甲組(不含日用百貨)/飲食業)","公共梯廳，管理委員會使用空間","公共梯廳"],"residentialFloorRecordCount":6,"officeFloorRecordCount":1,"retailFloorRecordCount":1,"parkingFloorRecordCount":2},"parkingSummary":{"parkingRecordCount":4,"carSpaces":14,"motorcycleSpaces":14},"remarksCount":22,"hasChangeSummary":false,"sourceDetailAvailable":true},{"id":"108|108使字第0116號","permitYearRaw":"108","permitYearRoc":108,"permitYearGregorian":2019,"permitNumber":"108使字第0116號","issueDateRaw":"1080612","issueDate":"2019-06-12","originalPermitNumber":"105雜字第0031號","constructionTypeRaw":"增建","constructionType":"addition","structureTypeRaw":"輕鋼架造(非供公眾使用建築物)","structureTypePrimary":"輕鋼架造","publicUseStatus":"non_public_use","zoningRaw":"住3","zoningCategory":"residential","district":"北投區","primaryAddress":"臺北市北投區榮華三路56號","addressCount":2,"addressesSample":["臺北市北投區榮華三路56號","臺北市北投區懷德街90號"],"landSectionCount":1,"landSectionsSample":["臺北市北投區振興段一小段0833-0010號"],"buildingInfo":{"buildingCount":0,"blockCount":0,"aboveGroundFloors":0,"undergroundFloors":0,"householdCount":0},"buildingArea":{"otherSiteAreaSqm":187,"buildingAreaSqm":0,"legalOpenSpaceAreaSqm":102.85,"aboveGroundShelterAreaSqm":0,"undergroundShelterAreaSqm":0},"buildingHeightM":17.35,"projectCostNtd":3660487,"completionDateRaw":"1080429","completionDate":"2019-04-29","startDateRaw":"1060904","startDate":"2017-09-04","floorSummary":{"floorRecordCount":0,"primaryUses":[],"residentialFloorRecordCount":0,"officeFloorRecordCount":0,"retailFloorRecordCount":0,"parkingFloorRecordCount":0},"parkingSummary":{"parkingRecordCount":0},"remarksCount":2,"hasChangeSummary":false,"sourceDetailAvailable":true},{"id":"108|108使字第0132號","permitYearRaw":"108","permitYearRoc":108,"permitYearGregorian":2019,"permitNumber":"108使字第0132號","issueDateRaw":"1080723","issueDate":"2019-07-23","originalPermitNumber":"106建字第0116號","constructionTypeRaw":"增建","constructionType":"addition","structureTypeRaw":"鋼構造、RC造、型鋼(供公眾使用建築物)","structureTypePrimary":"鋼構造","publicUseStatus":"public_use","zoningRaw":"醫療用地","zoningCategory":"other","district":"北投區","primaryAddress":"臺北市北投區石牌路二段322號","addressCount":1,"addressesSample":["臺北市北投區石牌路二段322號"],"landSectionCount":8,"landSectionsSample":["臺北市北投區崇仰段三小段0121-0000號","臺北市北投區崇仰段三小段0127-0000號","臺北市北投區崇仰段三小段0140-0000號"],"buildingInfo":{"buildingCount":0,"blockCount":0,"aboveGroundFloors":10,"undergroundFloors":0,"householdCount":0},"buildingArea":{"arcadeSiteAreaSqm":0,"otherSiteAreaSqm":29565.62,"buildingAreaSqm":0,"legalOpenSpaceAreaSqm":0,"aboveGroundShelterAreaSqm":0,"undergroundShelterAreaSqm":0},"buildingHeightM":36.7,"projectCostNtd":9163778,"completionDateRaw":"1070802","completionDate":"2018-08-02","startDateRaw":"1061204","startDate":"2017-12-04","floorSummary":{"floorRecordCount":2,"primaryUses":["實驗室、廚房、空調室、儲藏室、休息室(C-2)等供醫院使用。(原為屋突一層；原面積已計入容積計算。)","實驗室、廚房、空調室、儲藏室、休息室(C-2)等供醫院使用。(原為屋突二層；原面積已計入容積計算。)"],"residentialFloorRecordCount":0,"officeFloorRecordCount":0,"retailFloorRecordCount":0,"parkingFloorRecordCount":0},"parkingSummary":{"parkingRecordCount":2,"carSpaces":5,"motorcycleSpaces":8},"remarksCount":9,"hasChangeSummary":false,"sourceDetailAvailable":true},{"id":"108|108使字第0135號","permitYearRaw":"108","permitYearRoc":108,"permitYearGregorian":2019,"permitNumber":"108使字第0135號","issueDateRaw":"1080725","issueDate":"2019-07-25","originalPermitNumber":"103建字第0282號","constructionTypeRaw":"新建","constructionType":"new_construction","structureTypeRaw":"RC造(供公眾使用建築物)","structureTypePrimary":"RC造","publicUseStatus":"public_use","zoningRaw":"住3","zoningCategory":"residential","district":"北投區","primaryAddress":"臺北市北投區磺港路140號 2樓","addressCount":102,"addressesSample":["臺北市北投區磺港路140號 2樓","臺北市北投區磺港路140號 3樓","臺北市北投區磺港路140號 4樓"],"landSectionCount":1,"landSectionsSample":["臺北市北投區奇岩段四小段0011-0000號"],"buildingInfo":{"buildingCount":2,"blockCount":1,"aboveGroundFloors":18,"undergroundFloors":4,"householdCount":102},"buildingArea":{"arcadeSiteAreaSqm":0,"otherSiteAreaSqm":2866,"buildingAreaSqm":1260.51,"legalOpenSpaceAreaSqm":1576.3,"aboveGroundShelterAreaSqm":0,"undergroundShelterAreaSqm":1848.99},"buildingHeightM":59.9,"projectCostNtd":316644390,"completionDateRaw":"1080515","completionDate":"2019-05-15","startDateRaw":"1040630","startDate":"2015-06-30","floorSummary":{"floorRecordCount":25,"primaryUses":["防空避難室兼停車空間","停車空間","管委會使用空間595.41㎡,防災中心46.41㎡,車道157.51㎡,自行車停放區68.12㎡,樓電梯間290.77㎡。","集合住宅，(H2)","樓梯間"],"residentialFloorRecordCount":17,"officeFloorRecordCount":0,"retailFloorRecordCount":0,"parkingFloorRecordCount":4},"parkingSummary":{"parkingRecordCount":3,"carSpaces":143,"motorcycleSpaces":146},"remarksCount":28,"hasChangeSummary":false,"sourceDetailAvailable":true},{"id":"108|108使字第0154號","permitYearRaw":"108","permitYearRoc":108,"permitYearGregorian":2019,"permitNumber":"108使字第0154號","issueDateRaw":"1080829","issueDate":"2019-08-29","originalPermitNumber":"107雜字第0031號","constructionTypeRaw":"增建","constructionType":"addition","structureTypeRaw":"鋼骨造(供公眾使用建築物)","structureTypePrimary":"鋼骨造","publicUseStatus":"public_use","zoningRaw":"科技工業區","zoningCategory":"industrial","district":"北投區","primaryAddress":"臺北市北投區立德路121巷12號 1樓","addressCount":8,"addressesSample":["臺北市北投區立德路121巷12號 1樓","臺北市北投區立德路121巷12號 2樓","臺北市北投區立德路121巷12號 3樓"],"landSectionCount":1,"landSectionsSample":["臺北市北投區豐年段四小段0399-0000號"],"buildingInfo":{"buildingCount":0,"blockCount":0,"aboveGroundFloors":0,"undergroundFloors":0,"householdCount":0},"buildingArea":{"otherSiteAreaSqm":2044.13,"buildingAreaSqm":7.18,"legalOpenSpaceAreaSqm":0},"buildingHeightM":19,"projectCostNtd":1112000,"floorSummary":{"floorRecordCount":0,"primaryUses":[],"residentialFloorRecordCount":0,"officeFloorRecordCount":0,"retailFloorRecordCount":0,"parkingFloorRecordCount":0},"parkingSummary":{"parkingRecordCount":0},"remarksCount":1,"hasChangeSummary":false,"sourceDetailAvailable":true},{"id":"108|108使字第0156號","permitYearRaw":"108","permitYearRoc":108,"permitYearGregorian":2019,"permitNumber":"108使字第0156號","issueDateRaw":"1080909","issueDate":"2019-09-09","originalPermitNumber":"104建字第0205號","constructionTypeRaw":"新建","constructionType":"new_construction","structureTypeRaw":"RC造(供公眾使用建築物)","structureTypePrimary":"RC造","publicUseStatus":"public_use","zoningRaw":"住3","zoningCategory":"residential","district":"北投區","primaryAddress":"臺北市北投區致遠二路87巷28號 2樓","addressCount":21,"addressesSample":["臺北市北投區致遠二路87巷28號 2樓","臺北市北投區致遠二路87巷28號 3樓","臺北市北投區致遠二路87巷28號 4樓"],"landSectionCount":1,"landSectionsSample":["臺北市北投區立農段三小段0128-0000號"],"buildingInfo":{"buildingCount":1,"blockCount":1,"aboveGroundFloors":8,"undergroundFloors":1,"householdCount":21},"buildingArea":{"arcadeSiteAreaSqm":0,"otherSiteAreaSqm":396.77,"buildingAreaSqm":160.39,"legalOpenSpaceAreaSqm":197.2,"aboveGroundShelterAreaSqm":0,"undergroundShelterAreaSqm":195.2},"buildingHeightM":29.55,"projectCostNtd":18129927,"completionDateRaw":"1080503","completionDate":"2019-05-03","startDateRaw":"1050530","startDate":"2016-05-30","floorSummary":{"floorRecordCount":12,"primaryUses":["防空避難室195.2㎡,停車空間83.46㎡","停車空間(125.74㎡),樓電梯間(33.9㎡)","集合住宅(H2)","升降機間","機房"],"residentialFloorRecordCount":7,"officeFloorRecordCount":0,"retailFloorRecordCount":0,"parkingFloorRecordCount":2},"parkingSummary":{"parkingRecordCount":4,"carSpaces":10,"motorcycleSpaces":12},"remarksCount":23,"hasChangeSummary":false,"sourceDetailAvailable":true},{"id":"108|108使字第0182號","permitYearRaw":"108","permitYearRoc":108,"permitYearGregorian":2019,"permitNumber":"108使字第0182號","issueDateRaw":"1081018","issueDate":"2019-10-18","originalPermitNumber":"103建字第0153號","constructionTypeRaw":"新建","constructionType":"new_construction","structureTypeRaw":"RC造(非供公眾使用建築物)","structureTypePrimary":"RC造","publicUseStatus":"non_public_use","zoningRaw":"保護區","zoningCategory":"protection","district":"北投區","primaryAddress":"臺北市北投區西園街30號","addressCount":1,"addressesSample":["臺北市北投區西園街30號"],"landSectionCount":1,"landSectionsSample":["臺北市北投區大屯段二小段0399-0000號"],"buildingInfo":{"buildingCount":1,"blockCount":1,"aboveGroundFloors":3,"undergroundFloors":1,"householdCount":1},"buildingArea":{"arcadeSiteAreaSqm":0,"otherSiteAreaSqm":259.53,"buildingAreaSqm":60.82,"legalOpenSpaceAreaSqm":93.57,"aboveGroundShelterAreaSqm":0,"undergroundShelterAreaSqm":0},"buildingHeightM":10.5,"projectCostNtd":2306601,"completionDateRaw":"1061124","completionDate":"2017-11-24","startDateRaw":"1031029","startDate":"2014-10-29","floorSummary":{"floorRecordCount":4,"primaryUses":["獨立住宅"],"residentialFloorRecordCount":4,"officeFloorRecordCount":0,"retailFloorRecordCount":0,"parkingFloorRecordCount":0},"parkingSummary":{"parkingRecordCount":3,"carSpaces":3,"motorcycleSpaces":2},"remarksCount":16,"hasChangeSummary":false,"sourceDetailAvailable":true},{"id":"108|108使字第0186號","permitYearRaw":"108","permitYearRoc":108,"permitYearGregorian":2019,"permitNumber":"108使字第0186號","issueDateRaw":"1081105","issueDate":"2019-11-05","originalPermitNumber":"105建字第0081號","constructionTypeRaw":"新建","constructionType":"new_construction","structureTypeRaw":"RC造(非供公眾使用建築物)","structureTypePrimary":"RC造","publicUseStatus":"non_public_use","zoningRaw":"住3","zoningCategory":"residential","district":"北投區","primaryAddress":"臺北市北投區公館路255巷19弄6號","addressCount":1,"addressesSample":["臺北市北投區公館路255巷19弄6號"],"landSectionCount":1,"landSectionsSample":["臺北市北投區奇岩段三小段0077-0000號"],"buildingInfo":{"buildingCount":1,"blockCount":1,"aboveGroundFloors":5,"undergroundFloors":1,"householdCount":1},"buildingArea":{"arcadeSiteAreaSqm":0,"otherSiteAreaSqm":145,"buildingAreaSqm":72.26,"legalOpenSpaceAreaSqm":72.5,"aboveGroundShelterAreaSqm":0,"undergroundShelterAreaSqm":0},"buildingHeightM":16.7,"projectCostNtd":3070579,"completionDateRaw":"1080807","completionDate":"2019-08-07","startDateRaw":"1060113","startDate":"2017-01-13","floorSummary":{"floorRecordCount":7,"primaryUses":["機械室、電信室","(H2)獨立住宅(第一組)、停車空間","(H2)獨立住宅(第一組)","水箱、樓梯間"],"residentialFloorRecordCount":5,"officeFloorRecordCount":0,"retailFloorRecordCount":0,"parkingFloorRecordCount":0},"parkingSummary":{"parkingRecordCount":2,"carSpaces":3,"motorcycleSpaces":2},"remarksCount":18,"hasChangeSummary":false,"sourceDetailAvailable":true},{"id":"108|108使字第0189號","permitYearRaw":"108","permitYearRoc":108,"permitYearGregorian":2019,"permitNumber":"108使字第0189號","issueDateRaw":"1081107","issueDate":"2019-11-07","originalPermitNumber":"100建字第0277號","constructionTypeRaw":"新建","constructionType":"new_construction","structureTypeRaw":"RC造(供公眾使用建築物)","structureTypePrimary":"RC造","publicUseStatus":"public_use","zoningRaw":"住3","zoningCategory":"residential","district":"北投區","primaryAddress":"臺北市北投區新興路158巷1號 2樓","addressCount":19,"addressesSample":["臺北市北投區新興路158巷1號 2樓","臺北市北投區新興路158巷1號 3樓","臺北市北投區新興路158巷1號 4樓"],"landSectionCount":5,"landSectionsSample":["臺北市北投區桃源段二小段0353-0000號","臺北市北投區桃源段二小段0354-0000號","臺北市北投區桃源段二小段0355-0000號"],"buildingInfo":{"buildingCount":1,"blockCount":1,"aboveGroundFloors":10,"undergroundFloors":1,"householdCount":19},"buildingArea":{"arcadeSiteAreaSqm":0,"otherSiteAreaSqm":420,"buildingAreaSqm":188.45,"legalOpenSpaceAreaSqm":231.55,"aboveGroundShelterAreaSqm":0,"undergroundShelterAreaSqm":188.44},"buildingHeightM":36.7,"projectCostNtd":16857096,"completionDateRaw":"1050426","completionDate":"2016-04-26","startDateRaw":"1010710","startDate":"2012-07-10","floorSummary":{"floorRecordCount":14,"primaryUses":["防空避難室","一般零售業甲組(一~二九)(五金日用百貨除外)44.5㎡，(G3)，停車空間97.98㎡,(樓層高度部份3.6m,部分4.2m,平均高度3.74m)，公共梯間36.39㎡","(H2)集合住宅,(樓層高度部份3m,部分4.2m,平均高度3.6m)","(H2)集合住宅,(樓層高度部份3m,部分4.2m,平均高度3.6m)，集合住宅","梯廳"],"residentialFloorRecordCount":9,"officeFloorRecordCount":0,"retailFloorRecordCount":0,"parkingFloorRecordCount":1},"parkingSummary":{"parkingRecordCount":3,"carSpaces":11,"motorcycleSpaces":13},"remarksCount":22,"hasChangeSummary":false,"sourceDetailAvailable":true},{"id":"108|108使字第0206號","permitYearRaw":"108","permitYearRoc":108,"permitYearGregorian":2019,"permitNumber":"108使字第0206號","issueDateRaw":"1081203","issueDate":"2019-12-03","originalPermitNumber":"104建字第0211號","constructionTypeRaw":"新建","constructionType":"new_construction","structureTypeRaw":"RC造(供公眾使用建築物)","structureTypePrimary":"RC造","publicUseStatus":"public_use","zoningRaw":"住3","zoningCategory":"residential","district":"北投區","primaryAddress":"臺北市北投區中央北路二段173巷6號","addressCount":14,"addressesSample":["臺北市北投區中央北路二段173巷6號","臺北市北投區中央北路二段173巷6號 2樓","臺北市北投區中央北路二段173巷6號 3樓"],"landSectionCount":1,"landSectionsSample":["臺北市北投區豐年段二小段0349-0000號"],"buildingInfo":{"buildingCount":1,"blockCount":1,"aboveGroundFloors":7,"undergroundFloors":1,"householdCount":14},"buildingArea":{"arcadeSiteAreaSqm":0,"otherSiteAreaSqm":599.83,"buildingAreaSqm":247.8,"legalOpenSpaceAreaSqm":346.62,"aboveGroundShelterAreaSqm":0,"undergroundShelterAreaSqm":527.45},"buildingHeightM":21.72,"projectCostNtd":22147504,"completionDateRaw":"1061228","completionDate":"2017-12-28","startDateRaw":"1041229","startDate":"2015-12-29","floorSummary":{"floorRecordCount":10,"primaryUses":["防空避難室兼停車空間","集合住宅(H2)","樓梯間","蓄水池，機械室"],"residentialFloorRecordCount":7,"officeFloorRecordCount":0,"retailFloorRecordCount":0,"parkingFloorRecordCount":1},"parkingSummary":{"parkingRecordCount":4,"carSpaces":13,"motorcycleSpaces":15},"remarksCount":19,"hasChangeSummary":false,"sourceDetailAvailable":true},{"id":"108|108使字第0207號","permitYearRaw":"108","permitYearRoc":108,"permitYearGregorian":2019,"permitNumber":"108使字第0207號","issueDateRaw":"1081205","issueDate":"2019-12-05","originalPermitNumber":"106建字第0167號","constructionTypeRaw":"新建","constructionType":"new_construction","structureTypeRaw":"鋼骨造(非供公眾使用建築物)","structureTypePrimary":"鋼骨造","publicUseStatus":"non_public_use","zoningRaw":"保護區","zoningCategory":"protection","district":"北投區","primaryAddress":"臺北市北投區登山路136-6號","addressCount":2,"addressesSample":["臺北市北投區登山路136-6號","臺北市北投區登山路136-5號"],"landSectionCount":1,"landSectionsSample":["臺北市北投區泉源段三小段0166-0020號"],"buildingInfo":{"buildingCount":2,"blockCount":2,"aboveGroundFloors":1,"undergroundFloors":0,"householdCount":2},"buildingArea":{"arcadeSiteAreaSqm":0,"otherSiteAreaSqm":2512.48,"buildingAreaSqm":193.05,"legalOpenSpaceAreaSqm":2261.23,"aboveGroundShelterAreaSqm":0,"undergroundShelterAreaSqm":0},"buildingHeightM":5,"projectCostNtd":1852505,"completionDateRaw":"1080814","completionDate":"2019-08-14","startDateRaw":"1070605","startDate":"2018-06-05","floorSummary":{"floorRecordCount":2,"primaryUses":["第五十組農業倉庫","第四十九組溫室"],"residentialFloorRecordCount":0,"officeFloorRecordCount":0,"retailFloorRecordCount":0,"parkingFloorRecordCount":0},"parkingSummary":{"parkingRecordCount":2,"carSpaces":2,"motorcycleSpaces":2},"remarksCount":24,"hasChangeSummary":false,"sourceDetailAvailable":true},{"id":"108|108使字第0218號","permitYearRaw":"108","permitYearRoc":108,"permitYearGregorian":2019,"permitNumber":"108使字第0218號","issueDateRaw":"1081223","issueDate":"2019-12-23","originalPermitNumber":"101建字第0250號","constructionTypeRaw":"新建","constructionType":"new_construction","structureTypeRaw":"RC造(供公眾使用建築物)","structureTypePrimary":"RC造","publicUseStatus":"public_use","zoningRaw":"住2","zoningCategory":"residential","district":"北投區","primaryAddress":"臺北市北投區奇岩路241巷7弄10號","addressCount":75,"addressesSample":["臺北市北投區奇岩路241巷7弄10號","臺北市北投區奇岩路241巷7弄10號 2樓","臺北市北投區奇岩路241巷7弄10號 3樓"],"landSectionCount":1,"landSectionsSample":["臺北市北投區崇仰段二小段0499-0000號"],"buildingInfo":{"buildingCount":5,"blockCount":5,"aboveGroundFloors":5,"undergroundFloors":2,"householdCount":75},"buildingArea":{"arcadeSiteAreaSqm":0,"otherSiteAreaSqm":9664.37,"buildingAreaSqm":2275.81,"legalOpenSpaceAreaSqm":5960.04,"aboveGroundShelterAreaSqm":0,"undergroundShelterAreaSqm":2834.86},"buildingHeightM":17.4,"projectCostNtd":183841108,"completionDateRaw":"1080529","completionDate":"2019-05-29","startDateRaw":"1020620","startDate":"2013-06-20","floorSummary":{"floorRecordCount":37,"primaryUses":["防空避難室兼停車空間，地下一層：A棟(358.25㎡)、DE棟(1079.86㎡)、F棟(758.07㎡)、停車空間:B棟(638.68㎡)","防空避難室兼停車空間，地下二層：B棟(638.68㎡)、停車空間:DE棟(1079.86㎡)、F棟(758.07㎡)","門廳:29.55㎡，供管委會使用空間：85.58㎡，集合住宅(H2):165.12㎡","集合住宅(H2)","樓電梯間、水錶室"],"residentialFloorRecordCount":24,"officeFloorRecordCount":0,"retailFloorRecordCount":0,"parkingFloorRecordCount":2},"parkingSummary":{"parkingRecordCount":2,"carSpaces":90,"motorcycleSpaces":216},"remarksCount":28,"hasChangeSummary":false,"sourceDetailAvailable":true},{"id":"108|108使字第0224號","permitYearRaw":"108","permitYearRoc":108,"permitYearGregorian":2019,"permitNumber":"108使字第0224號","issueDateRaw":"1081226","issueDate":"2019-12-26","originalPermitNumber":"102建字第0328號","constructionTypeRaw":"新建","constructionType":"new_construction","structureTypeRaw":"鋼骨RC造(非供公眾使用建築物)","structureTypePrimary":"鋼骨RC造","publicUseStatus":"non_public_use","zoningRaw":"商三特(原住三)、住3","zoningCategory":"residential","district":"北投區","primaryAddress":"臺北市北投區天母西路115號 4樓之2","addressCount":51,"addressesSample":["臺北市北投區天母西路115號 4樓之2","臺北市北投區天母西路115號 5樓之2","臺北市北投區天母西路115號 6樓之2"],"landSectionCount":2,"landSectionsSample":["臺北市北投區崇仰段三小段0068-0000號","臺北市北投區崇仰段三小段0092-0000號"],"buildingInfo":{"buildingCount":1,"blockCount":1,"aboveGroundFloors":21,"undergroundFloors":4,"householdCount":51},"buildingArea":{"arcadeSiteAreaSqm":0,"otherSiteAreaSqm":2245.45,"buildingAreaSqm":595.54,"legalOpenSpaceAreaSqm":1006.9,"aboveGroundShelterAreaSqm":0,"undergroundShelterAreaSqm":1569.61},"buildingHeightM":73.35,"projectCostNtd":215348792,"completionDateRaw":"1081204","completionDate":"2019-12-04","startDateRaw":"1030318","startDate":"2014-03-18","floorSummary":{"floorRecordCount":28,"primaryUses":["配電室、機房、受電室、電氣室，防空避難室兼停車空間","停車空間，機電設備空間","停車空間，蓄水池，機電設備空間","(G3)供一般零售業(甲組)(日用百貨除外)93.06㎡，一般事務所5.25㎡，外廊14.08㎡，戶內遊憩設施13.66㎡，管理員室3.70㎡，門廳272.89㎡，陽台超過2M6.29㎡，車道55.13㎡，樓電梯間84.86㎡","(H2)集合住宅"],"residentialFloorRecordCount":20,"officeFloorRecordCount":1,"retailFloorRecordCount":0,"parkingFloorRecordCount":4},"parkingSummary":{"parkingRecordCount":5,"carSpaces":132,"motorcycleSpaces":112},"remarksCount":24,"hasChangeSummary":false,"sourceDetailAvailable":true}]
